<?xml version='1.0' encoding='utf-8'?>
<!-- FreeCAD DocumentObject -->
<Document SchemaVersion="4" FileVersion="2">
<Object name="Pocket042">
  <Properties Count="40" TransientCount="2">
    <_Property name="_Body" type="App::PropertyLinkHidden" status="251658241"/>
    <_Property name="_ElementMapVersion" type="App::PropertyString" status="234881024"/>
    <Property name="AddSubShape" type="Part::PropertyPartShape" status="1">
      <Part ElementMap="0.15.70200.4" brep="1">
<![CDATA[

CASCADE Topology V1, (c) Matra-Datavision
Locations 7
1
              1               0               0               0 
              0               1               0               0 
              0               0               1               0 
1
              1               0          -4e-15          -6e-14 
         -4e-15               0              -1             -16 
              0               1               0           4e-15 
2  1 1 2 1 0
1
              1               0               0         2.6e-14 
              0               1               0               7 
              0               0               1          -2e-15 
2  1 1 2 1 4 1 0
2  2 -1 1 -1 0
2  4 -1 2 -1 1 -1 0
Curve2ds 20
1 43.485673828538886 7.6999999999999999e-16 0 -1 
1 0 0 0 -1 
1 -0 0 0 -1 
1 39.999999999999993 -1.03e-15 0 -1 
1 0 0 1 -0 
1 -3.9999999999999999e-16 -7 1 -0 
1 19.999999999999996 -21.742836914269446 -1 0 
1 43.485673828538886 1.0000000000000001e-15 0 -1 
1 0 0 -0 -1 
1 -0 0 1 0 
1 -1.5499999999999999e-15 -7 1 0 
1 -20 -21.742836914269446 0 1 
1 0 0 0 -1 
1 40 -7.4999999999999996e-16 -0 -1 
1 -20 21.742836914269439 1 -0 
1 0 0 1 0 
1 -4.93e-15 -7 1 0 
1 0 0 1 0 
1 -5.5499999999999999e-15 -7 1 0 
1 19.999999999999996 21.742836914269439 -0 -1 
Curves 8
1 4.5000000000079394 -15.999999999999964 103.4999997466802 3.7499999999999998e-15 1 -2.2e-16 
1 -35.499999999992056 -15.999999999999813 103.4999997466802 3.7499999999999998e-15 1 -2.2e-16 
1 4.5000000000079998 103.4999997466802 0 -1 0 0 
1 -35.499999999992056 -15.999999999999824 60.014325918141317 3.7499999999999998e-15 1 -2.2e-16 
1 -35.499999999991999 103.4999997466802 0 0 -1 0 
1 4.5000000000079403 -15.999999999999973 60.014325918141317 3.7499999999999998e-15 1 -2.2e-16 
1 -35.499999999991999 60.01432591814131 0 1 0 0 
1 4.5000000000079998 60.01432591814131 0 0 1 0 
Polygon3D 0
PolygonOnTriangulations 0
Surfaces 5
1 4.5000000000079394 -15.999999999999964 103.4999997466802 0 2.2e-16 1 -1 3.7499999999999998e-15 -8.2499999999999989e-31 -3.7499999999999998e-15 -1 2.2e-16 
1 4.5000000000079394 -15.999999999999973 60.014325918141317 1 -3.7499999999999998e-15 0 8.2499999999999989e-31 2.2e-16 1 -3.7499999999999998e-15 -1 2.2e-16 
1 -35.499999999992056 -15.999999999999813 103.4999997466802 -1 3.7499999999999998e-15 -0 -8.2499999999999989e-31 -2.2e-16 -1 -3.7499999999999998e-15 -1 2.2e-16 
1 -15.499999999992058 -15.999999999999897 81.757162832410756 3.7499999999999998e-15 1 -2.2e-16 1 -3.7499999999999998e-15 0 -8.2499999999999989e-31 -2.2e-16 -1 
1 -35.499999999992056 -15.999999999999824 60.014325918141317 -0 -2.2e-16 -1 1 -3.7499999999999998e-15 8.2499999999999989e-31 -3.7499999999999998e-15 -1 2.2e-16 
Triangulations 0

TShapes 24
Ve
1e-07
4.500000000008 103.49999974668 0
0 0

0101101
*
Ed
 1e-07 1 1 0
1  1 0 0 7
2  1 2 0 0 7
2  2 1 0 0 7
0

0101000
+24 3 -24 5 *
Ve
1e-07
-35.499999999992 103.49999974668 0
0 0

0101101
*
Ed
 1e-07 1 1 0
1  2 0 0 7
2  3 3 0 0 7
2  4 1 0 0 7
0

0101000
+22 3 -22 5 *
Ed
 1e-07 1 1 0
1  3 0 0 40
2  5 1 6 0 40
2  6 1 7 0 40
2  7 4 6 0 40
0

0101000
+24 0 -22 0 *
Wi

0101100
+23 0 -21 0 -20 3 +20 5 *
Fa
0  1e-07 1 0

0111000
+19 0 *
Ve
1e-07
-35.499999999992 60.0143259181413 0
0 0

0101101
*
Ed
 1e-07 1 1 0
1  4 0 0 7
2  8 3 0 0 7
2  9 5 0 0 7
0

0101000
+17 3 -17 5 *
Ed
 1e-07 1 1 0
1  5 0 0 43.4856738285389
2  10 3 6 0 43.4856738285389
2  11 3 7 0 43.4856738285389
2  12 4 6 0 43.4856738285389
0

0101000
+22 0 -17 0 *
Wi

0101100
+21 0 -16 0 -15 3 +15 5 *
Fa
0  1e-07 3 0

0111000
+14 0 *
Ve
1e-07
4.500000000008 60.0143259181413 0
0 0

0101101
*
Ed
 1e-07 1 1 0
1  6 0 0 7
2  13 2 0 0 7
2  14 5 0 0 7
0

0101000
+12 3 -12 5 *
Ed
 1e-07 1 1 0
1  7 0 0 40
2  15 4 6 0 40
2  16 5 6 0 40
2  17 5 7 0 40
0

0101000
+17 0 -12 0 *
Wi

0101100
+16 0 -11 0 -10 3 +10 5 *
Fa
0  1e-07 5 0

0111000
+9 0 *
Ed
 1e-07 1 1 0
1  8 0 0 43.4856738285389
2  18 2 6 0 43.4856738285389
2  19 2 7 0 43.4856738285389
2  20 4 6 0 43.4856738285389
0

0101000
+12 0 -24 0 *
Wi

0101100
+11 0 -23 0 -7 3 +7 5 *
Fa
0  1e-07 2 0

0111000
+6 0 *
Wi

0101100
+20 0 +15 0 +10 0 +7 0 *
Fa
0  1e-07 4 0

0111000
-4 3 *
Sh

0101100
-18 0 -13 0 -8 0 -5 0 +3 0 -3 4 *
So

1100000
-2 0 *

+1 0 ]]>
      </Part>
      <ElementMap/>
    </Property>
    <Property name="AddSubType" type="App::PropertyEnumeration" status="1">
      <Integer value="1"/>
    </Property>
    <Property name="AllowMultiFace" type="App::PropertyBool" status="1">
      <Bool value="true"/>
    </Property>
    <Property name="AutoTaperInnerAngle" type="App::PropertyBool" status="1">
      <Bool value="false"/>
    </Property>
    <Property name="BaseFeature" type="App::PropertyLink" status="9">
      <Link value="Pad012"/>
    </Property>
    <Property name="CheckUpToFaceLimits" type="App::PropertyBool" status="1">
      <Bool value="true"/>
    </Property>
    <Property name="ClaimChildren" type="App::PropertyBool" status="134217729">
      <Bool value="false"/>
    </Property>
    <Property name="ColoredElements" type="App::PropertyLinkSubHidden" status="218103809">
      <LinkSub value="" count="0">
      </LinkSub>
    </Property>
    <Property name="ExpressionEngine" type="App::PropertyExpressionEngine" status="67108864">
      <ExpressionEngine count="0"></ExpressionEngine>
    </Property>
    <Property name="Fit" type="App::PropertyDistance" status="1">
      <Float value="0"/>
    </Property>
    <Property name="FitJoin" type="App::PropertyEnumeration" status="1">
      <Integer value="0"/>
    </Property>
    <Property name="InnerFit" type="App::PropertyDistance" status="1">
      <Float value="0"/>
    </Property>
    <Property name="InnerFitJoin" type="App::PropertyEnumeration" status="1">
      <Integer value="0"/>
    </Property>
    <Property name="Label" type="App::PropertyString" status="134217729">
      <String value="Pocket042"/>
    </Property>
    <Property name="Label2" type="App::PropertyString" status="128">
      <String value=""/>
    </Property>
    <Property name="Length" type="App::PropertyLength" status="1">
      <Float value="7"/>
    </Property>
    <Property name="Length2" type="App::PropertyLength" status="1">
      <Float value="5"/>
    </Property>
    <Property name="Linearize" type="App::PropertyBool" status="1">
      <Bool value="false"/>
    </Property>
    <Property name="Midplane" type="App::PropertyBool" status="1">
      <Bool value="false"/>
    </Property>
    <Property name="NewSolid" type="App::PropertyBool" status="1">
      <Bool value="false"/>
    </Property>
    <Property name="Offset" type="App::PropertyLength" status="1">
      <Float value="0"/>
    </Property>
    <Property name="Placement" type="App::PropertyPlacement" status="8388621">
      <PropertyPlacement Px="0" Py="0" Pz="0" Q0="0" Q1="0" Q2="0" Q3="1" A="0" Ox="0" Oy="0" Oz="1"/>
    </Property>
    <Property name="Profile" type="App::PropertyLinkSub" status="1">
      <LinkSub value="Sketch053" count="0">
      </LinkSub>
    </Property>
    <Property name="Refine" type="App::PropertyBool" status="1">
      <Bool value="false"/>
    </Property>
    <Property name="Reversed" type="App::PropertyBool" status="1">
      <Bool value="false"/>
    </Property>
    <Property name="Shape" type="Part::PropertyPartShape" status="1">
      <Part ElementMap="0.15.70200.4" brep="1">
<![CDATA[

CASCADE Topology V1, (c) Matra-Datavision
Locations 30
1
              1               0               0               0 
              0               1               0               0 
              0               0               1               0 
1
             -1               0           4e-15 2.14432703314124 
          4e-15               0               1         2.7e-14 
             -0               1              -0 -12.9221933393662 
2  1 1 2 1 0
1
             -1               0           4e-15 2.14432703314124 
          4e-15               0               1         2.7e-14 
             -0               1              -0 -12.9221933393662 
1
              1               0               0               0 
              0               1               0               0 
              0               0               1               0 
2  4 -1 5 -1 0
1
              1               0               0       -1.38e-13 
              0               1               0             -37 
              0               0               1           8e-15 
2  7 -1 4 -1 5 -1 0
1
             -1               0           4e-15 2.14432703314124 
          4e-15               0               1         2.7e-14 
             -0               1              -0 -12.9221933393662 
1
              1               0               0               0 
              0               1               0               0 
              0               0               1               0 
2  9 -1 10 -1 0
1
              1               0               0     -3.1308e-11 
              0               1               0 -8393.44929740233 
              0               0               1       1.864e-12 
2  12 -1 9 -1 10 -1 0
2  2 -1 1 -1 0
1
              1               0               0     -3.1308e-11 
              0               1               0 -8393.44929740233 
              0               0               1       1.864e-12 
2  15 -1 2 -1 1 -1 0
1
              1               0               0         2.6e-14 
              0               1               0               7 
              0               0               1          -2e-15 
1
              1               0               0               0 
              0               1               0               0 
              0               0               1               0 
1
              1               0          -4e-15          -6e-14 
         -4e-15               0              -1             -16 
              0               1               0           4e-15 
2  18 1 19 1 17 1 0
2  19 -1 18 -1 0
2  17 -1 19 -1 18 -1 0
1
              1               0               0               0 
              0               1               0               0 
              0               0               1               0 
1
              1               0               0               0 
              0               1               0               0 
              0               0               1               0 
1
              1               0               0               0 
              0               1               0               0 
              0               0               1               0 
1
              1               0               0               0 
              0               1               0               0 
              0               0               1               0 
1
              1               0               0               0 
              0               1               0               0 
              0               0               1               0 
1
              1               0               0               0 
              0               1               0               0 
              0               0               1               0 
1
              1               0               0               0 
              0               1               0               0 
              0               0               1               0 
2  23 -1 24 -1 25 -1 26 -1 27 -1 28 -1 29 -1 0
Curve2ds 432
1 -19.899999999462189 4.501828057596299 -0 -1 
1 0 0 1 0 
1 5.9999999999999997e-15 -37 1 0 
1 9.5999999999999943 -4.9699999999999999e-15 1 0 
1 -19.900000000000006 20.449999999999989 -0 -1 
1 0 0 1 0 
1 5.0099999999999998e-15 -8393.4492974023324 1 0 
1 0 0 1 0 
1 5.0099999999999998e-15 -8393.4492974023324 1 0 
1 -19.899999999462189 4.501828057596299 -0 -1 
1 34 0 0 -1 
1 0 0 0 -1 
8 -19.621418457134709 7.3642553714041696
1 14.378581542865289 -9.0000000000000107 -1 -0 
8 -19.621418457134709 7.3642553714041696
1 -19.89999992193162 14.378581542865277 0 1 
8 1.0000000000000027 7.999314057492672
1 7.0143261714611267 -8.0000000000000036 0 -1 
8 1.0000000000000027 7.999314057492672
1 0.10000007806837473 -8.0000000000000036 2.0000000000000001e-17 1 
8 -34.109598007775062 -0.1095980077750589
1 -0.1095980077750589 -15.999314057492583 -1 2.7000000000000001e-15 
8 -34.109598007775062 -0.1095980077750589
1 0.10959800777501272 -19.901946993911174 -1 0 
1 0 0 0 -1 
1 2.6000000000000014 0 -0 -1 
1 -17.299999999462187 4.501828057596299 -1 0 
1 0 0 1 0 
1 4.1000000000000004e-15 -37 1 0 
1 -17.300000000000004 20.449999999999989 -1 0 
1 0 0 1 0 
1 6.0500000000000001e-15 -8393.4492974023324 1 0 
1 0 0 1 0 
1 6.0500000000000001e-15 -8393.4492974023324 1 0 
1 -17.299999999462187 4.501828057596299 -1 0 
1 -17.299999999462187 4.501828057596299 0 1 
1 -0 0 1 0 
1 -5.9999999999999997e-15 -37 1 0 
1 -0 0 1 0 
1 -5.0099999999999998e-15 -8393.4492974023324 1 0 
1 -0 0 1 0 
1 -5.0099999999999998e-15 -8393.4492974023324 1 0 
1 -17.299999999462187 4.501828057596299 0 1 
1 -17.299999999462187 43.501828057596299 1 -0 
1 0 0 1 -0 
1 -4.1000000000000004e-15 -37 1 -0 
1 0 0 1 -0 
1 -6.0500000000000001e-15 -8393.4492974023324 1 -0 
1 0 0 1 -0 
1 -6.0500000000000001e-15 -8393.4492974023324 1 -0 
1 -17.299999999462187 43.501828057596299 1 -0 
1 17.300000000537818 43.501828057596299 -0 -1 
1 0 0 1 0 
1 6.7000000000000004e-16 -37 1 0 
1 0 0 1 0 
1 -3.2000000000000002e-16 -8393.4492974023324 1 0 
1 0 0 1 0 
1 -3.2000000000000002e-16 -8393.4492974023324 1 0 
1 17.300000000537818 43.501828057596299 -0 -1 
1 19.900000000537819 4.501828057596299 -1 0 
1 0 0 1 0 
1 5.4999999999999996e-16 -37 1 0 
1 19.900000000000006 20.449999999999989 -1 0 
1 0 0 1 0 
1 7.1999999999999997e-16 -8393.4492974023324 1 0 
1 0 0 1 0 
1 7.1999999999999997e-16 -8393.4492974023324 1 0 
1 19.900000000537819 4.501828057596299 -1 0 
1 19.900000000537819 -29.498171942403701 0 1 
1 -0 0 1 0 
1 -5.9999999999999997e-15 -37 1 0 
1 16.499999999999972 -3.6600000000000003e-15 1 0 
1 19.900000000000006 -13.550000000000011 0 1 
1 -0 0 1 0 
1 2.0999999999999998e-15 -8393.4492974023324 1 0 
1 -0 0 1 0 
1 2.0999999999999998e-15 -8393.4492974023324 1 0 
1 19.900000000537819 -29.498171942403701 0 1 
1 19.900000000537819 -29.498171942403701 -0.31622776601683728 -0.94868329805051399 
1 0 0 1 0 
1 6.1400000000000004e-15 -37 1 0 
1 19.900000000000006 -13.550000000000011 -0.31622776601683728 -0.94868329805051399 
1 0 0 1 0 
1 -2.04e-15 -8393.4492974023324 1 0 
1 0 0 1 0 
1 -2.04e-15 -8393.4492974023324 1 0 
1 19.900000000537819 -29.498171942403701 -0.31622776601683728 -0.94868329805051399 
1 17.900000000537819 -45.998171942403715 0 1 
1 -0 0 1 0 
1 -5.9999999999999997e-15 -36.999999999999993 1 0 
1 17.900000000000006 -30.050000000000026 0 1 
1 -0 0 1 0 
1 2.0999999999999998e-15 -8393.4492974023324 1 0 
1 -0 0 1 0 
1 2.0999999999999998e-15 -8393.4492974023324 1 0 
1 17.900000000537819 -45.998171942403715 0 1 
1 12.900000000537819 -45.998171942403715 1 -0 
1 0 0 1 -0 
1 -9.9999999999999998e-17 -37 1 -0 
1 32.800000000000011 -1.5499999999999999e-15 1 -0 
1 12.900000000000004 -30.050000000000026 1 -0 
1 0 0 1 -0 
1 1.6000000000000001e-16 -8393.4492974023324 1 -0 
1 0 0 1 -0 
1 1.6000000000000001e-16 -8393.4492974023324 1 -0 
1 12.900000000537819 -45.998171942403715 1 -0 
1 12.900000000537819 -40.998171942403701 -0 -1 
1 0 0 1 0 
1 5.9999999999999997e-15 -37 1 0 
1 12.900000000000004 -25.050000000000011 -0 -1 
1 0 0 1 0 
1 -2.0999999999999998e-15 -8393.4492974023324 1 0 
1 0 0 1 0 
1 -2.0999999999999998e-15 -8393.4492974023324 1 0 
1 12.900000000537819 -40.998171942403701 -0 -1 
1 0 0 1 0 
1 0 -37 1 0 
2 10.900000000537819 -40.998171942403701 -1 0 -0 -1 2
2 10.900000000000004 -25.050000000000011 -1 0 -0 -1 2
1 0 0 1 0 
1 0 -8393.4492974023324 1 0 
1 0 0 1 0 
1 0 -8393.4492974023324 1 0 
2 10.900000000537819 -40.998171942403701 -1 0 -0 -1 2
1 -10.899999999462191 -38.998171942403701 1 -0 
1 0 0 1 -0 
1 -5.4999999999999996e-16 -37 1 -0 
1 -10.900000000000006 -23.050000000000011 1 -0 
1 0 0 1 -0 
1 1.0499999999999999e-15 -8393.4492974023324 1 -0 
1 0 0 1 -0 
1 1.0499999999999999e-15 -8393.4492974023324 1 -0 
1 -10.899999999462191 -38.998171942403701 1 -0 
1 0 0 1 0 
1 0 -37 1 0 
2 -10.899999999462191 -40.998171942403701 -1 0 -0 -1 2
2 -10.900000000000006 -25.050000000000011 -1 0 -0 -1 2
1 0 0 1 0 
1 0 -8393.4492974023324 1 0 
1 0 0 1 0 
1 0 -8393.4492974023324 1 0 
2 -10.899999999462191 -40.998171942403701 -1 0 -0 -1 2
1 -12.899999999462191 -45.998171942403715 0 1 
1 -0 0 1 0 
1 -5.9999999999999997e-15 -36.999999999999993 1 0 
1 -12.900000000000006 -30.050000000000026 0 1 
1 -0 0 1 0 
1 2.0999999999999998e-15 -8393.4492974023324 1 0 
1 -0 0 1 0 
1 2.0999999999999998e-15 -8393.4492974023324 1 0 
1 -12.899999999462191 -45.998171942403715 0 1 
1 -17.899999999462189 -45.998171942403715 1 -0 
1 0 0 1 -0 
1 -4.1000000000000004e-15 -37 1 -0 
1 2 -3.5000000000000002e-16 1 -0 
1 -17.900000000000006 -30.050000000000026 1 -0 
1 0 0 1 -0 
1 -6.0500000000000001e-15 -8393.4492974023324 1 -0 
1 0 0 1 -0 
1 -6.0500000000000001e-15 -8393.4492974023324 1 -0 
1 -17.899999999462189 -45.998171942403715 1 -0 
1 -17.899999999462189 -35.498171942403715 -0 -1 
1 0 0 1 0 
1 5.9999999999999997e-15 -37 1 0 
1 -17.900000000000006 -19.550000000000026 -0 -1 
1 0 0 1 0 
1 -2.0999999999999998e-15 -8393.4492974023324 1 0 
1 0 0 1 0 
1 -2.0999999999999998e-15 -8393.4492974023324 1 0 
1 -17.899999999462189 -35.498171942403715 -0 -1 
1 -19.899999999462189 -29.498171942403701 0.31622776601683728 -0.94868329805051399 
1 0 0 1 0 
1 6.6399999999999998e-15 -37 1 0 
1 -19.900000000000006 -13.550000000000011 0.31622776601683728 -0.94868329805051399 
1 0 0 1 0 
1 -1.66e-15 -8393.4492974023324 1 0 
1 0 0 1 0 
1 -1.66e-15 -8393.4492974023324 1 0 
1 -19.899999999462189 -29.498171942403701 0.31622776601683728 -0.94868329805051399 
1 15.500000000537808 10.961984539327005 -1 0 
1 0 0 1 0 
1 9.9999999999999998e-17 -37 1 0 
1 15.499999999999993 26.910156481730695 -1 0 
1 0 0 1 0 
1 -1.6000000000000001e-16 -8393.4492974023324 1 0 
1 0 0 1 0 
1 -1.6000000000000001e-16 -8393.4492974023324 1 0 
1 15.500000000537808 10.961984539327005 -1 0 
1 -15.500000003864637 10.961984539327005 0 1 
1 -0 0 1 0 
1 -5.9999999999999997e-15 -37 1 0 
1 -0 0 1 0 
1 -5.0099999999999998e-15 -8393.4492974023324 1 0 
1 -0 0 1 0 
1 -5.0099999999999998e-15 -8393.4492974023324 1 0 
1 -15.500000003864637 10.961984539327005 0 1 
1 -15.500000003864637 41.501828057596299 1 -0 
1 0 0 1 -0 
1 -5.4999999999999996e-16 -37 1 -0 
1 7.3673852799999995e-08 -2 1 0 
1 7.3673852799999995e-08 -2 1 0 
1 7.3673852799999995e-08 -2 1 0 
1 0 0 1 -0 
1 1.0499999999999999e-15 -8393.4492974023324 1 -0 
1 0 0 1 -0 
1 1.0499999999999999e-15 -8393.4492974023324 1 -0 
1 -15.500000003864637 41.501828057596299 1 -0 
1 15.500000000537808 41.501828057596299 -0 -1 
1 0 0 1 0 
1 6.7000000000000004e-16 -37 1 0 
1 0 0 1 0 
1 -3.2000000000000002e-16 -8393.4492974023324 1 0 
1 0 0 1 0 
1 -3.2000000000000002e-16 -8393.4492974023324 1 0 
1 15.500000000537808 41.501828057596299 -0 -1 
1 0 0 1 0 
1 0 -37 1 0 
2 14.400000000537819 -11.998171942403715 -1 0 -0 -1 2.5
2 14.400000000000004 3.9499999999999744 -1 0 -0 -1 2.5
1 0 0 1 0 
1 0 -8393.4492974023324 1 0 
1 0 0 1 0 
1 0 -8393.4492974023324 1 0 
2 14.400000000537819 -11.998171942403715 -1 0 -0 -1 2.5
1 14.400000000537819 -9.4981719424037152 -1 0 
1 0 0 1 0 
1 9.9999999999999998e-17 -37 1 0 
1 14.400000000000004 6.4499999999999744 -1 0 
1 0 0 1 0 
1 -1.6000000000000001e-16 -8393.4492974023324 1 0 
1 0 0 1 0 
1 -1.6000000000000001e-16 -8393.4492974023324 1 0 
1 14.400000000537819 -9.4981719424037152 -1 0 
1 0 0 1 0 
1 0 -37 1 0 
2 -14.399999999462176 -11.998171942403715 -1 0 -0 -1 2.4999999999999964
2 -14.399999999999991 3.9499999999999744 -1 0 -0 -1 2.5
1 0 0 1 0 
1 0 -8393.4492974023324 1 0 
1 0 0 1 0 
1 0 -8393.4492974023324 1 0 
2 -14.399999999462176 -11.998171942403715 -1 0 -0 -1 2.4999999999999964
1 -16.899999999462175 -11.998171942403715 -0 -1 
1 0 0 1 0 
1 5.9999999999999997e-15 -36.999999999999993 1 0 
1 -16.899999999999991 3.9499999999999744 -0 -1 
1 0 0 1 0 
1 -2.0999999999999998e-15 -8393.4492974023324 1 0 
1 0 0 1 0 
1 -2.0999999999999998e-15 -8393.4492974023324 1 0 
1 -16.899999999462175 -11.998171942403715 -0 -1 
1 -16.899999999462175 -29.498171942403701 0.31622776601683711 -0.9486832980505141 
1 0 0 1 0 
1 6.6399999999999998e-15 -37 1 0 
1 -16.899999999999991 -13.550000000000011 0.31622776601683711 -0.9486832980505141 
1 0 0 1 0 
1 -1.66e-15 -8393.4492974023324 1 0 
1 0 0 1 0 
1 -1.66e-15 -8393.4492974023324 1 0 
1 -16.899999999462175 -29.498171942403701 0.31622776601683711 -0.9486832980505141 
1 0 0 1 0 
1 0 -37 1 0 
2 -13.458481559349922 -33.498171942403715 -1 0 -0 -1 2
2 -13.458481559887737 -17.550000000000026 -1 0 -0 -1 2
1 0 0 1 0 
1 0 -8393.4492974023324 1 0 
1 0 0 1 0 
1 0 -8393.4492974023324 1 0 
2 -13.458481559349922 -33.498171942403715 -1 0 -0 -1 2
1 13.458481560425565 -35.498171942403715 -1 0 
1 0 0 1 0 
1 9.9999999999999998e-17 -36.999999999999993 1 0 
1 13.458481559887749 -19.550000000000026 -1 0 
1 0 0 1 0 
1 -1.6000000000000001e-16 -8393.4492974023324 1 0 
1 0 0 1 0 
1 -1.6000000000000001e-16 -8393.4492974023324 1 0 
1 13.458481560425565 -35.498171942403715 -1 0 
1 0 0 1 0 
1 0 -37 1 0 
2 13.458481560425565 -33.498171942403715 -1 0 -0 -1 1.9999999999999996
2 13.458481559887749 -17.550000000000026 -1 0 -0 -1 2
1 0 0 1 0 
1 0 -8393.4492974023324 1 0 
1 0 0 1 0 
1 0 -8393.4492974023324 1 0 
2 13.458481560425565 -33.498171942403715 -1 0 -0 -1 1.9999999999999996
1 16.900000000537819 -29.498171942403701 -0.31622776601683739 -0.94868329805051399 
1 0 0 1 0 
1 6.2800000000000003e-15 -36.999999999999993 1 0 
1 16.900000000000006 -13.550000000000011 -0.31622776601683739 -0.94868329805051399 
1 0 0 1 0 
1 -2.1799999999999999e-15 -8393.4492974023324 1 0 
1 0 0 1 0 
1 -2.1799999999999999e-15 -8393.4492974023324 1 0 
1 16.900000000537819 -29.498171942403701 -0.31622776601683739 -0.94868329805051399 
1 16.900000000537819 -11.998171942403715 -0 -1 
1 0 0 1 0 
1 5.9999999999999997e-15 -37 1 0 
1 16.900000000000006 3.9499999999999744 -0 -1 
1 0 0 1 0 
1 -2.0999999999999998e-15 -8393.4492974023324 1 0 
1 0 0 1 0 
1 -2.0999999999999998e-15 -8393.4492974023324 1 0 
1 16.900000000537819 -11.998171942403715 -0 -1 
1 0 0 0 -1 
1 6.3245553203367715 -0 0 -1 
8 -5.6649849682979898 0.65957035203878622
1 0.65957035203878445 -9.0000000000000107 -1 0 
8 -5.6649849682979898 0.65957035203878622
1 -19.691425462975456 -5.8685602911379249 -0.31622776601683728 0.94868329805051399 
1 0 0 1 -0 
1 -3.9999999999999999e-16 -7 1 -0 
1 19.999999999999996 -21.742836914269446 -1 0 
1 7.0999999219316177 -9.0000000000000089 -1 2.0000000000000001e-17 
8 -13.371418457134725 -8.3714184571347072
1 -8.3714184571347108 -9.0000000000000107 -1 -0 
8 -13.371418457134725 -8.3714184571347072
1 12.900000078068381 -8.3714184571347232 0 1 
1 0 -9.0000000000000107 1 0 
2 10.900000078068381 -16.742836914269432 -1 0 -0 -1 2
8 -16.350000039034192 5.4499999609658136
1 5.4499999609658136 -9.0000000000000107 -1 2.0000000000000001e-17 
8 -16.350000039034192 5.4499999609658136
1 -5.4499999609658154 -14.742836914269432 -1 0 
1 0 -9.0000000000000107 1 0 
2 -10.899999921931627 -16.742836914269432 -1 0 -0 -1 2
8 5.8714184571347072 10.871418457134725
1 10.871418457134725 -9.0000000000000124 -1 0 
8 5.8714184571347072 10.871418457134725
1 -12.899999921931627 -10.871418457134723 -0 -1 
1 37.899999921931624 -9.0000000000000071 -1 2.0000000000000001e-17 
8 -16.121418457134723 -5.6214184571347214
1 -5.621418457134725 -9.0000000000000107 -1 -0 
8 -16.121418457134723 -5.6214184571347214
1 -17.89999992193162 -5.6214184571347232 0 1 
1 -20 21.742836914269439 1 -0 
1 0 0 1 0 
1 -4.93e-15 -7 1 0 
8 -24.36425537140417 2.6214184571347112
1 2.6214184571347112 -9.0000000000000124 -1 0 
8 -24.36425537140417 2.6214184571347112
1 19.900000078068381 -2.6214184571347232 -0 -1 
8 -5.6649849436106043 0.65957037672617125
1 0.65957037672616947 -9.0000000000000089 -1 -1.0000000000000001e-17 
8 -5.6649849436106043 0.65957037672617125
1 19.69142561130538 -5.8685603145584366 0.31622776601683728 0.94868329805051399 
8 0.37141845713472321 10.871418457134725
1 10.871418457134725 -9.0000000000000107 -1 0 
8 0.37141845713472321 10.871418457134725
1 17.900000078068381 -10.871418457134723 -0 -1 
1 0 -9.0000000000000107 1 0 
2 14.400000078068381 12.257163085730554 -1 0 -0 -1 2.5
8 -21.599999960965803 7.2000000390341903
1 7.2000000390341903 -9.0000000000000107 -1 -2.0000000000000001e-17 
8 -21.599999960965803 7.2000000390341903
1 7.2000000390341903 14.757163085730554 1 -0 
1 0 -9.0000000000000107 1 0 
2 -14.399999921931613 12.257163085730554 -1 0 -0 -1 2.5
8 -11.371418457134711 6.1285815428652768
1 6.128581542865275 -9.0000000000000107 -1 -0 
8 -11.371418457134711 6.1285815428652768
1 -16.899999921931606 6.1285815428652768 0 1 
8 -4.6978081772109945 0.18522870301352479
1 0.18522870301352301 -9.0000000000000107 -1 0 
8 -4.6978081772109945 0.18522870301352479
1 -16.841425462975447 -5.418560291137922 -0.31622776601683711 0.9486832980505141 
1 0 -9.0000000000000107 1 0 
2 -13.458481481819359 -9.2428369142694464 -1 0 -0 -1 2
8 -20.187722300797425 6.729240818978063
1 6.729240818978063 -9.0000000000000107 -1 -2.0000000000000001e-17 
8 -20.187722300797425 6.729240818978063
1 6.729240818978063 -11.242836914269446 1 -0 
1 0 -9.0000000000000107 1 0 
2 13.458481637956126 -9.2428369142694464 -1 0 -0 -1 2
8 -4.6978081525235948 0.18522872770092658
1 0.1852287277009248 -9.0000000000000107 -1 -1.0000000000000001e-17 
8 -4.6978081525235948 0.18522872770092658
1 16.841425611305375 -5.418560314558448 0.31622776601683739 0.94868329805051399 
8 -11.371418457134711 6.1285815428652768
1 6.128581542865275 -9.0000000000000107 -1 -0 
8 -11.371418457134711 6.1285815428652768
1 16.900000078068381 6.1285815428652768 0 1 
8 -29.899026542078602 9.9009734579214115
1 7.2335221870111965 -10.000973535989777 -0 -1 
8 -29.899026542078602 9.9009734579214115
1 10.000973535989775 -0.00068594250744188998 -1 3.6499999999999998e-15 
8 -7.9993140574925263 -1.0000000000000027
1 26.985673828538875 -8.0000000000000053 0 1 
8 -7.9993140574925263 -1.0000000000000027
1 39.900000078068381 -8.0000000000000036 -2.0000000000000001e-17 -1 
8 -11.250973496955627 -8.6509734969556185
1 -8.6509734969556185 -15.999314057492542 -1 3.6300000000000002e-15 
8 -11.250973496955627 -8.6509734969556185
1 0.21919601555006807 -8.6509734969555598 -0 1 
8 -38.890401992224938 0.10959800777506391
1 0.1095980077750589 -15.999314057492574 -1 -2.7000000000000001e-15 
8 -38.890401992224938 0.10959800777506391
1 0.10959800777501272 -17.30194699391118 1 -0 
8 -25.94902650304439 8.6509734969556238
1 8.6509734969556185 -15.999314057492438 -1 -3.6300000000000002e-15 
8 -25.94902650304439 8.6509734969556238
1 -38.780803984449932 -8.6509734969555598 0 -1 
8 -19.609598007775059 19.390401992224941
1 19.390401992224941 -15.999314057492395 -1 2.7000000000000001e-15 
8 -19.609598007775059 19.390401992224941
1 -19.390401992224987 17.298053006088825 -1 0 
8 7.3490265030443815 9.949026503044383
1 9.949026503044383 -15.999314057492477 -1 3.6300000000000002e-15 
8 7.3490265030443815 9.949026503044383
1 0.21919601555006807 9.9490265030444434 -0 1 
8 -16.890401992224934 17.109598007775066
1 17.109598007775066 -15.999314057492485 -1 -2.7000000000000001e-15 
8 -16.890401992224934 17.109598007775066
1 17.109598007775006 19.898053006088826 1 -0 
8 -23.250973501358065 7.7490265030443792
1 7.7490265030443792 -15.999314057492464 -1 3.6300000000000002e-15 
8 -23.250973501358065 7.7490265030443792
1 -6.2409604661806384 7.749026503044437 -0 1 
8 -33.660323751359591 -3.1204802330902894
1 -3.1204802330902943 -15.999314057492558 -1 -2.7000000000000001e-15 
8 -33.660323751359591 -3.1204802330902894
1 -3.1204802330903405 -15.501946998313629 1 -0 
8 -12.149441526044356 18.390401992224941
1 18.390401992224941 -15.999314057492404 -1 2.7000000000000001e-15 
8 -12.149441526044356 18.390401992224941
1 -18.390401992224987 15.498053006088815 -1 0 
8 -23.249026505245599 7.7509734991568449
1 7.7509734991568449 -15.999314057492441 -1 -3.6300000000000002e-15 
8 -23.249026505245599 7.7509734991568449
1 -36.780803984449932 -7.7509734991567836 0 -1 
1 7.7509734991568386 -1.9999999999999982 -1 0 
1 0 0 -0 -1 
1 -0 0 0 -1 
1 39 0 0 -1 
1 0 0 0 -1 
1 34.600000000000001 -0 0 -1 
1 -0 -0 0 -1 
1 39 0 0 -1 
1 2.6000000000000005 0 -0 -1 
1 0 0 -0 -1 
1 34 0 0 -1 
1 -0 0 0 -1 
1 0 0 0 -1 
1 6.3245553203367724 0 0 -1 
1 10.5 0 0 -1 
1 -0 0 0 -1 
1 5 0 0 -1 
1 0 0 0 -1 
1 5.0000000000000142 -0 0 -1 
1 3.1415926535897944 0 0 -1 
1 0 0 0 -1 
1 4.7123889803846897 0 0 -1 
1 21.800000000000008 0 0 -1 
1 4.7123889803846897 0 0 -1 
1 0 0 0 -1 
1 6.2831853071795845 0 0 -1 
1 5.0000000000000142 0 0 -1 
1 -0 0 0 -1 
1 4.9999999999999964 -0 0 -1 
1 0 0 0 -1 
1 10.5 0 0 -1 
1 31.000000004402445 0 -0 -1 
1 -0 0 0 -1 
1 0 0 -0 -1 
1 30.539843518269294 0 0 -1 
1 30.539843518269294 -0 0 -1 
1 0 0 0 -1 
1 31.000000004402445 0 0 -1 
1 0 0 0 -1 
1 4.7123889803846897 0 0 -1 
1 0 0 -0 -1 
1 3.141592653589794 0 0 -1 
1 0 0 0 -1 
1 4.7123889803846897 0 0 -1 
1 28.799999999999994 0 -0 -1 
1 6.2831853071795845 0 0 -1 
1 0 0 0 -1 
1 17.499999999999986 0 0 -1 
1 0 0 0 -1 
1 0.3217505543966403 0 0 -1 
1 4.8830368802245179 0 0 -1 
1 1.5707963267948972 0 0 -1 
1 26.916963119775485 -0 -0 -1 
1 1.5707963267948963 0 0 -1 
1 8.9000000000000007e-16 -0 -0 -1 
1 2.819842099193151 0 0 -1 
1 4.8830368802245179 -0 -0 -1 
1 0 0 -0 -1 
1 17.499999999999986 0 0 -1 
Curves 101
1 37.544326955064868 65.922193086046391 0 0 1 0 
1 -35.399999921923623 1.8893000000000001e-13 86.999999746680189 -3.7300000000000003e-15 -1 2.2e-16 
1 -35.399999921923651 -8.9999999999998259 67.37858128954548 -0 -2.2e-16 -1 
1 -35.399999921923651 -7.9999999999998206 60.014325918141317 -3.7300000000000003e-15 -1 2.2e-16 
1 -35.39999992192368 -15.999314057492402 52.890401738905133 0 2.4800000000000001e-15 -1 
1 -35.399999921923623 1.8138000000000001e-13 52.999999746680189 -3.7300000000000003e-15 -1 2.2e-16 
1 34.944326955064867 65.922193086046391 0 1 0 0 
1 34.944326955064867 65.922193086046391 0 0 -1 0 
1 34.944326955064867 26.922193086046388 0 -1 0 0 
1 0.34432695506485927 26.922193086046388 0 0 1 0 
1 -2.2556730449351408 65.922193086046391 0 1 0 0 
1 -2.2556730449351408 99.922193086046391 0 0 -1 0 
1 -2.2556730449351408 99.922193086046391 0 0.31622776601683728 0.94868329805051399 0 
1 -0.25567304493514087 116.42219308604641 0 0 -1 0 
1 4.7443269550648592 116.42219308604641 0 -1 0 0 
1 4.7443269550648592 111.42219308604639 0 0 1 0 
2 6.7443269550648592 111.42219308604639 0 0 0 1 1 0 -0 -0 1 0 2
1 28.544326955064868 109.42219308604639 0 -1 0 0 
2 28.544326955064868 111.42219308604639 0 0 0 1 1 0 -0 -0 1 0 2
1 30.544326955064868 116.42219308604641 0 0 -1 0 
1 35.544326955064868 116.42219308604641 0 -1 0 0 
1 35.544326955064868 105.92219308604641 0 0 1 0 
1 37.544326955064868 99.922193086046391 0 -0.31622776601683728 0.94868329805051399 0 
1 2.1443269550648694 59.462036604315685 0 1 0 0 
1 33.144326959467314 59.462036604315685 0 0 -1 0 
1 33.144326959467314 28.922193086046388 0 -1 0 0 
1 2.1443269550648694 28.922193086046388 0 0 1 0 
2 3.2443269550648592 82.422193086046406 0 0 0 1 1 0 -0 -0 1 0 2.5
1 3.2443269550648592 79.922193086046406 0 1 0 0 
2 32.044326955064854 82.422193086046406 0 0 0 1 1 0 -0 -0 1 0 2.5
1 34.544326955064854 82.422193086046406 0 0 1 0 
1 34.544326955064854 99.922193086046391 0 -0.31622776601683711 0.9486832980505141 0 
2 31.102808514952599 103.92219308604641 0 0 0 1 1 0 -0 -0 1 0 2
1 4.1858453951771137 105.92219308604641 0 1 0 0 
2 4.1858453951771137 103.92219308604641 0 0 0 1 1 0 -0 -0 1 0 2
1 0.74432695506485913 99.922193086046391 0 0.31622776601683739 0.94868329805051399 0 
1 0.74432695506485913 82.422193086046406 0 0 1 0 
1 -33.399999921923623 1.8279999999999999e-13 92.999999746680203 -3.7300000000000003e-15 -1 2.2e-16 
1 -35.191425462967487 -8.9999999999998224 87.625723123548681 -0.31622776601683728 9.6999999999999998e-16 -0.94868329805051399 
1 4.5000000000079998 103.4999997466802 0 -1 0 0 
1 -2.5999999219236507 -8.9999999999999432 90.12858128954548 -0 -2.2e-16 -1 
2 -4.5999999219236507 -8.9999999999999343 98.499999746680189 3.7300000000000003e-15 1 -2.2e-16 -1 3.7300000000000003e-15 0 8.2060000000000005e-31 2.2e-16 1 2
1 -20.949999960957847 -8.9999999999998721 96.499999746680189 -1 3.7499999999999998e-15 -0 
2 -26.399999921923659 -8.9999999999998526 98.499999746680189 3.7300000000000003e-15 1 -2.2e-16 -1 3.7300000000000003e-15 0 8.2060000000000005e-31 2.2e-16 1 2
1 -28.399999921923659 -8.9999999999998472 92.62858128954548 0 2.2e-16 1 
1 -33.399999921923651 -8.9999999999998295 87.37858128954548 -0 -2.2e-16 -1 
1 -35.499999999991999 60.01432591814131 0 1 0 0 
1 4.4000000780763493 -8.9999999999999716 84.37858128954548 0 2.2e-16 1 
1 4.191425611313349 -8.999999999999968 87.625723146969193 0.31622776601683728 -1.4000000000000001e-15 -0.94868329805051399 
1 2.4000000780763493 -8.9999999999999609 92.62858128954548 0 2.2e-16 1 
2 -1.0999999219236509 -8.9999999999999538 69.499999746680203 3.7300000000000003e-15 1 -2.2e-16 -1 3.7300000000000003e-15 0 8.2060000000000005e-31 2.2e-16 1 2.5
1 -8.299999960957841 -8.9999999999999272 66.999999746680203 1 -3.7499999999999998e-15 0 
2 -29.899999921923644 -8.9999999999998455 69.499999746680203 3.7300000000000003e-15 1 -2.2e-16 -1 3.7300000000000003e-15 0 8.2060000000000005e-31 2.2e-16 1 2.5
1 -32.399999921923637 -8.9999999999998348 75.62858128954548 -0 -2.2e-16 -1 
1 -32.341425462967479 -8.999999999999833 87.175723123548678 -0.31622776601683711 9.6999999999999998e-16 -0.9486832980505141 
2 -28.95848148181139 -8.9999999999998455 90.999999746680203 3.7300000000000003e-15 1 -2.2e-16 -1 3.7300000000000003e-15 0 8.2060000000000005e-31 2.2e-16 1 2
1 -8.7707591810139682 -8.9999999999999201 92.999999746680203 1 -3.7499999999999998e-15 0 
2 -2.0415183620359056 -8.9999999999999449 90.999999746680203 3.7300000000000003e-15 1 -2.2e-16 -1 3.7300000000000003e-15 0 8.2060000000000005e-31 2.2e-16 1 2
1 1.341425611313344 -8.9999999999999591 87.175723146969204 0.31622776601683739 -1.4000000000000001e-15 -0.94868329805051399 
1 1.4000000780763493 -8.9999999999999609 75.62858128954548 -0 -2.2e-16 -1 
1 -25.499026464002281 -15.99931405749242 60.014325918141317 -1 9.9999999999999998e-17 0 
1 4.4000000780763537 -7.9999999999999698 60.014325918141317 3.7300000000000003e-15 1 -2.2e-16 
1 -24.149026424968064 -15.999314057492402 52.999999746680189 1 -9.9999999999999998e-17 -0 
1 -32.799999921923686 -15.999314057492402 52.890401738905133 -0 -2.4800000000000001e-15 1 
1 -24.149026424968064 -15.999314057492306 13.99999974668019 -1 9.9999999999999998e-17 0 
1 1.8000000780763221 -15.999314057492358 33.390401738905133 0 2.4800000000000001e-15 -1 
1 -5.5490264249680612 -15.999314057492406 52.999999746680189 1 -9.9999999999999998e-17 -0 
1 4.4000000780763227 -15.999314057492448 69.890401738905126 -0 -2.4800000000000001e-15 1 
1 -7.7490264249680667 -15.999314057492388 46.539843264949482 1 -9.9999999999999998e-17 -0 
1 -30.999999926326133 -15.999314057492395 49.66032349803978 -0 -2.4800000000000001e-15 1 
1 7.8076312219999997e-08 -15.999314057492359 34.390401738905133 0 2.4800000000000001e-15 -1 
1 -23.249026427169287 -15.999314057492313 15.99999974668019 -1 9.9999999999999998e-17 0 
1 -32.799999921923622 1.7168000000000001e-13 52.999999746680189 -3.7300000000000003e-15 -1 2.2e-16 
1 -32.799999921923622 1.6302e-13 13.999999746680192 -3.7300000000000003e-15 -1 2.2e-16 
1 1.8000000780763832 3.3960000000000001e-14 13.999999746680189 -3.7300000000000003e-15 -1 2.2e-16 
1 1.8000000780763825 4.2619999999999999e-14 52.999999746680189 -3.7300000000000003e-15 -1 2.2e-16 
1 4.400000078076383 3.292e-14 52.999999746680189 -3.7300000000000003e-15 -1 2.2e-16 
1 4.400000078076383 4.0469999999999997e-14 86.999999746680189 -3.7300000000000003e-15 -1 2.2e-16 
1 2.4000000780763826 4.9270000000000001e-14 92.999999746680203 -3.7300000000000003e-15 -1 2.2e-16 
1 2.4000000780763826 5.1600000000000002e-14 103.4999997466802 -3.7300000000000003e-15 -1 2.2e-16 
1 -2.5999999219236174 7.0250000000000004e-14 103.4999997466802 -3.7300000000000003e-15 -1 2.2e-16 
1 -2.5999999219236174 6.9139999999999996e-14 98.499999746680189 -3.7300000000000003e-15 -1 2.2e-16 
1 -4.5999999219236187 7.6149999999999996e-14 96.499999746680189 -3.7300000000000003e-15 -1 2.2e-16 
1 -26.399999921923627 1.5747000000000001e-13 96.499999746680189 -3.7300000000000003e-15 -1 2.2e-16 
1 -28.399999921923627 1.6537000000000001e-13 98.499999746680189 -3.7300000000000003e-15 -1 2.2e-16 
1 -28.399999921923627 1.6647999999999999e-13 103.4999997466802 -3.7300000000000003e-15 -1 2.2e-16 
1 -33.399999921923623 1.8512999999999999e-13 103.4999997466802 -3.7300000000000003e-15 -1 2.2e-16 
1 -30.999999926326073 1.6353000000000001e-13 46.539843264949482 -3.7300000000000003e-15 -1 2.2e-16 
1 7.8076372479999995e-08 4.7900000000000003e-14 46.539843264949482 -3.7300000000000003e-15 -1 2.2e-16 
1 -30.999999926326073 1.5674999999999999e-13 15.999999746680189 -3.7300000000000003e-15 -1 2.2e-16 
1 7.8076372479999995e-08 4.1119999999999999e-14 15.999999746680189 -3.7300000000000003e-15 -1 2.2e-16 
1 -1.0999999219236174 5.6550000000000003e-14 66.999999746680203 -3.7300000000000003e-15 -1 2.2e-16 
1 1.4000000780763826 4.7779999999999999e-14 69.499999746680203 -3.7300000000000003e-15 -1 2.2e-16 
1 -29.899999921923612 1.6397000000000001e-13 66.999999746680203 -3.7300000000000003e-15 -1 2.2e-16 
1 -32.399999921923609 1.7385000000000001e-13 69.499999746680203 -3.7300000000000003e-15 -1 2.2e-16 
1 -32.399999921923609 1.7774000000000001e-13 86.999999746680189 -3.7300000000000003e-15 -1 2.2e-16 
1 -30.855848077912388 1.7301000000000001e-13 91.632455278713877 -3.7300000000000003e-15 -1 2.2e-16 
1 -28.958481481811358 1.6622999999999999e-13 92.999999746680203 -3.7300000000000003e-15 -1 2.2e-16 
1 -2.0415183620358728 6.5829999999999996e-14 92.999999746680203 -3.7300000000000003e-15 -1 2.2e-16 
1 -0.14415176593484391 5.8450000000000006e-14 91.632455278713877 -3.7300000000000003e-15 -1 2.2e-16 
1 1.4000000780763826 5.1659999999999998e-14 86.999999746680189 -3.7300000000000003e-15 -1 2.2e-16 
Polygon3D 0
PolygonOnTriangulations 0
Surfaces 110
1 -35.399999921923623 1.8138000000000001e-13 52.999999746680189 -1 3.7300000000000003e-15 -0 8.2060000000000005e-31 2.2e-16 1 3.7300000000000003e-15 1 -2.2e-16 
1 -15.499999922461436 1.0815e-13 57.501827804276488 3.7300000000000003e-15 1 -2.2e-16 1 -3.7300000000000003e-15 0 -8.2060000000000005e-31 -2.2e-16 -1 
1 -35.399999921923623 1.8138000000000001e-13 52.999999746680189 -1 3.7300000000000003e-15 -0 8.2060000000000005e-31 2.2e-16 1 3.7300000000000003e-15 1 -2.2e-16 
1 -35.399999921923765 -36.999999999999822 43.399999746680209 1 -3.7300000000000003e-15 0 8.2060000000000005e-31 2.2e-16 1 -3.7300000000000003e-15 -1 2.2e-16 
1 -15.499999921923759 -36.999999999999893 73.449999746680191 3.7499999999999998e-15 1 -2.4e-16 1 -3.7499999999999998e-15 0 -8.999999999999999e-31 -2.4e-16 -1 
1 -35.399999921923623 1.8138000000000001e-13 52.999999746680189 -1 3.7300000000000003e-15 -0 8.2060000000000005e-31 2.2e-16 1 3.7300000000000003e-15 1 -2.2e-16 
1 -15.499999922461436 1.0815e-13 57.501827804276488 3.7300000000000003e-15 1 -2.2e-16 1 -3.7300000000000003e-15 0 -8.2060000000000005e-31 -2.2e-16 -1 
1 -35.399999921923623 1.8893000000000001e-13 86.999999746680189 -0.94868329805051399 3.6099999999999999e-15 0.31622776601683728 0.31622776601683728 -9.6999999999999998e-16 0.94868329805051399 3.7314876389986877e-15 1 -2.2135943621178385e-16 
1 -15.499999999992058 -15.999999999999897 81.757162832410756 3.7499999999999998e-15 1 -2.2e-16 1 -3.7499999999999998e-15 0 -8.2499999999999989e-31 -2.2e-16 -1 
1 -35.499999999992056 -15.999999999999824 60.014325918141317 -0 -2.2e-16 -1 1 -3.7499999999999998e-15 8.2499999999999989e-31 -3.7499999999999998e-15 -1 2.2e-16 
10 -1018.2852732789535 1030.2236653100535 -999.40641628841456 999.40252230059241
1 -15.498052928012504 -15.999314057492404 52.780803731130121 9.9999999999999998e-17 1 2.4800000000000001e-15 0 -2.4800000000000001e-15 1 1 -9.9999999999999998e-17 -2.4800000000000001e-31 
1 -32.799999921923622 1.7168000000000001e-13 52.999999746680189 -0 -2.2e-16 -1 -1 3.7300000000000003e-15 -8.2060000000000005e-31 3.7300000000000003e-15 1 -2.2e-16 
1 -32.799999921923622 1.7168000000000001e-13 52.999999746680189 -0 -2.2e-16 -1 -1 3.7300000000000003e-15 -8.2060000000000005e-31 3.7300000000000003e-15 1 -2.2e-16 
1 -32.799999921923622 1.7168000000000001e-13 52.999999746680189 -0 -2.2e-16 -1 -1 3.7300000000000003e-15 -8.2060000000000005e-31 3.7300000000000003e-15 1 -2.2e-16 
1 -32.799999921923622 1.7168000000000001e-13 52.999999746680189 1 -3.7300000000000003e-15 0 -8.2060000000000005e-31 -2.2e-16 -1 3.7300000000000003e-15 1 -2.2e-16 
1 -32.799999921923622 1.7168000000000001e-13 52.999999746680189 1 -3.7300000000000003e-15 0 -8.2060000000000005e-31 -2.2e-16 -1 3.7300000000000003e-15 1 -2.2e-16 
1 -32.799999921923622 1.7168000000000001e-13 52.999999746680189 1 -3.7300000000000003e-15 0 -8.2060000000000005e-31 -2.2e-16 -1 3.7300000000000003e-15 1 -2.2e-16 
1 -32.799999921923622 1.6302e-13 13.999999746680189 0 2.2e-16 1 1 -3.7300000000000003e-15 8.2060000000000005e-31 3.7300000000000003e-15 1 -2.2e-16 
1 -32.799999921923622 1.6302e-13 13.999999746680189 0 2.2e-16 1 1 -3.7300000000000003e-15 8.2060000000000005e-31 3.7300000000000003e-15 1 -2.2e-16 
1 -32.799999921923622 1.6302e-13 13.999999746680189 0 2.2e-16 1 1 -3.7300000000000003e-15 8.2060000000000005e-31 3.7300000000000003e-15 1 -2.2e-16 
1 1.8000000780763825 3.3960000000000001e-14 13.999999746680189 -1 3.7300000000000003e-15 -0 8.2060000000000005e-31 2.2e-16 1 3.7300000000000003e-15 1 -2.2e-16 
1 1.8000000780763825 3.3960000000000001e-14 13.999999746680189 -1 3.7300000000000003e-15 -0 8.2060000000000005e-31 2.2e-16 1 3.7300000000000003e-15 1 -2.2e-16 
1 1.8000000780763825 3.3960000000000001e-14 13.999999746680189 -1 3.7300000000000003e-15 -0 8.2060000000000005e-31 2.2e-16 1 3.7300000000000003e-15 1 -2.2e-16 
1 4.400000078076383 3.292e-14 52.999999746680189 -0 -2.2e-16 -1 -1 3.7300000000000003e-15 -8.2060000000000005e-31 3.7300000000000003e-15 1 -2.2e-16 
1 4.400000078076383 3.292e-14 52.999999746680189 -0 -2.2e-16 -1 -1 3.7300000000000003e-15 -8.2060000000000005e-31 3.7300000000000003e-15 1 -2.2e-16 
1 4.400000078076383 3.292e-14 52.999999746680189 -0 -2.2e-16 -1 -1 3.7300000000000003e-15 -8.2060000000000005e-31 3.7300000000000003e-15 1 -2.2e-16 
1 4.400000078076383 4.0469999999999997e-14 86.999999746680189 1 -3.7300000000000003e-15 0 -8.2060000000000005e-31 -2.2e-16 -1 3.7300000000000003e-15 1 -2.2e-16 
1 4.4000000780762436 -36.999999999999957 103.49999974668017 -1 3.7300000000000003e-15 -0 -8.2060000000000005e-31 -2.2e-16 -1 -3.7300000000000003e-15 -1 2.2e-16 
1 4.400000078076383 4.0469999999999997e-14 86.999999746680189 1 -3.7300000000000003e-15 0 -8.2060000000000005e-31 -2.2e-16 -1 3.7300000000000003e-15 1 -2.2e-16 
1 4.400000078076383 4.0469999999999997e-14 86.999999746680189 1 -3.7300000000000003e-15 0 -8.2060000000000005e-31 -2.2e-16 -1 3.7300000000000003e-15 1 -2.2e-16 
1 4.400000078076383 4.0469999999999997e-14 86.999999746680189 -0.94868329805051399 3.47e-15 -0.31622776601683728 -0.31622776601683728 1.3899999999999997e-15 0.94868329805051399 3.7314876389986869e-15 1 -2.2135943621178878e-16 
1 4.400000078076383 4.0469999999999997e-14 86.999999746680189 -0.94868329805051399 3.47e-15 -0.31622776601683728 -0.31622776601683728 1.3899999999999997e-15 0.94868329805051399 3.7314876389986869e-15 1 -2.2135943621178878e-16 
1 4.400000078076383 4.0469999999999997e-14 86.999999746680189 -0.94868329805051399 3.47e-15 -0.31622776601683728 -0.31622776601683728 1.3899999999999997e-15 0.94868329805051399 3.7314876389986869e-15 1 -2.2135943621178878e-16 
1 2.4000000780763826 5.1600000000000002e-14 103.4999997466802 1 -3.7300000000000003e-15 0 -8.2060000000000005e-31 -2.2e-16 -1 3.7300000000000003e-15 1 -2.2e-16 
1 2.4000000780763826 5.1600000000000002e-14 103.4999997466802 1 -3.7300000000000003e-15 0 -8.2060000000000005e-31 -2.2e-16 -1 3.7300000000000003e-15 1 -2.2e-16 
1 2.4000000780763826 5.1600000000000002e-14 103.4999997466802 1 -3.7300000000000003e-15 0 -8.2060000000000005e-31 -2.2e-16 -1 3.7300000000000003e-15 1 -2.2e-16 
1 -2.5999999219236174 7.0250000000000004e-14 103.4999997466802 0 2.2e-16 1 1 -3.7300000000000003e-15 8.2060000000000005e-31 3.7300000000000003e-15 1 -2.2e-16 
1 -35.399999921923765 -36.999999999999808 103.49999974668017 -0 -2.2e-16 -1 1 -3.7300000000000003e-15 8.2060000000000005e-31 -3.7300000000000003e-15 -1 2.2e-16 
1 -2.5999999219236174 7.0250000000000004e-14 103.4999997466802 0 2.2e-16 1 1 -3.7300000000000003e-15 8.2060000000000005e-31 3.7300000000000003e-15 1 -2.2e-16 
1 -2.5999999219236174 7.0250000000000004e-14 103.4999997466802 0 2.2e-16 1 1 -3.7300000000000003e-15 8.2060000000000005e-31 3.7300000000000003e-15 1 -2.2e-16 
1 -2.5999999219236174 6.9139999999999996e-14 98.499999746680189 -1 3.7300000000000003e-15 -0 8.2060000000000005e-31 2.2e-16 1 3.7300000000000003e-15 1 -2.2e-16 
1 -2.5999999219236174 6.9139999999999996e-14 98.499999746680189 -1 3.7300000000000003e-15 -0 8.2060000000000005e-31 2.2e-16 1 3.7300000000000003e-15 1 -2.2e-16 
1 -2.5999999219236174 6.9139999999999996e-14 98.499999746680189 -1 3.7300000000000003e-15 -0 8.2060000000000005e-31 2.2e-16 1 3.7300000000000003e-15 1 -2.2e-16 
2 -4.599999921923617 7.6599999999999997e-14 98.499999746680189 3.7300000000000003e-15 1 -2.2e-16 -1 3.7300000000000003e-15 0 8.2060000000000005e-31 2.2e-16 1 2
2 -4.599999921923617 7.6599999999999997e-14 98.499999746680189 3.7300000000000003e-15 1 -2.2e-16 -1 3.7300000000000003e-15 0 8.2060000000000005e-31 2.2e-16 1 2
2 -4.599999921923617 7.6599999999999997e-14 98.499999746680189 3.7300000000000003e-15 1 -2.2e-16 -1 3.7300000000000003e-15 0 8.2060000000000005e-31 2.2e-16 1 2
1 -26.399999921923627 1.5747000000000001e-13 96.499999746680189 0 2.2e-16 1 1 -3.7300000000000003e-15 8.2060000000000005e-31 3.7300000000000003e-15 1 -2.2e-16 
1 -26.399999921923627 1.5747000000000001e-13 96.499999746680189 0 2.2e-16 1 1 -3.7300000000000003e-15 8.2060000000000005e-31 3.7300000000000003e-15 1 -2.2e-16 
1 -26.399999921923627 1.5747000000000001e-13 96.499999746680189 0 2.2e-16 1 1 -3.7300000000000003e-15 8.2060000000000005e-31 3.7300000000000003e-15 1 -2.2e-16 
2 -26.399999921923627 1.5791000000000001e-13 98.499999746680189 3.7300000000000003e-15 1 -2.2e-16 -1 3.7300000000000003e-15 0 8.2060000000000005e-31 2.2e-16 1 2
2 -26.399999921923627 1.5791000000000001e-13 98.499999746680189 3.7300000000000003e-15 1 -2.2e-16 -1 3.7300000000000003e-15 0 8.2060000000000005e-31 2.2e-16 1 2
2 -26.399999921923627 1.5791000000000001e-13 98.499999746680189 3.7300000000000003e-15 1 -2.2e-16 -1 3.7300000000000003e-15 0 8.2060000000000005e-31 2.2e-16 1 2
1 -28.399999921923627 1.6647999999999999e-13 103.4999997466802 1 -3.7300000000000003e-15 0 -8.2060000000000005e-31 -2.2e-16 -1 3.7300000000000003e-15 1 -2.2e-16 
1 -28.399999921923627 1.6647999999999999e-13 103.4999997466802 1 -3.7300000000000003e-15 0 -8.2060000000000005e-31 -2.2e-16 -1 3.7300000000000003e-15 1 -2.2e-16 
1 -28.399999921923627 1.6647999999999999e-13 103.4999997466802 1 -3.7300000000000003e-15 0 -8.2060000000000005e-31 -2.2e-16 -1 3.7300000000000003e-15 1 -2.2e-16 
1 -33.399999921923623 1.8512999999999999e-13 103.4999997466802 0 2.2e-16 1 1 -3.7300000000000003e-15 8.2060000000000005e-31 3.7300000000000003e-15 1 -2.2e-16 
1 -33.399999921923623 1.8512999999999999e-13 103.4999997466802 0 2.2e-16 1 1 -3.7300000000000003e-15 8.2060000000000005e-31 3.7300000000000003e-15 1 -2.2e-16 
1 -33.399999921923623 1.8512999999999999e-13 103.4999997466802 0 2.2e-16 1 1 -3.7300000000000003e-15 8.2060000000000005e-31 3.7300000000000003e-15 1 -2.2e-16 
1 -33.399999921923623 1.8279999999999999e-13 92.999999746680203 -1 3.7300000000000003e-15 -0 8.2060000000000005e-31 2.2e-16 1 3.7300000000000003e-15 1 -2.2e-16 
1 -33.399999921923623 1.8279999999999999e-13 92.999999746680203 -1 3.7300000000000003e-15 -0 8.2060000000000005e-31 2.2e-16 1 3.7300000000000003e-15 1 -2.2e-16 
1 -33.399999921923623 1.8279999999999999e-13 92.999999746680203 -1 3.7300000000000003e-15 -0 8.2060000000000005e-31 2.2e-16 1 3.7300000000000003e-15 1 -2.2e-16 
1 -35.399999921923623 1.8893000000000001e-13 86.999999746680189 -0.94868329805051399 3.6099999999999999e-15 0.31622776601683728 0.31622776601683728 -9.6999999999999998e-16 0.94868329805051399 3.7314876389986877e-15 1 -2.2135943621178385e-16 
1 -35.399999921923623 1.8893000000000001e-13 86.999999746680189 -0.94868329805051399 3.6099999999999999e-15 0.31622776601683728 0.31622776601683728 -9.6999999999999998e-16 0.94868329805051399 3.7314876389986877e-15 1 -2.2135943621178385e-16 
1 7.8076372479999995e-08 4.7900000000000003e-14 46.539843264949482 -0 -2.2e-16 -1 -1 3.7300000000000003e-15 -8.2060000000000005e-31 3.7300000000000003e-15 1 -2.2e-16 
1 7.8076372479999995e-08 4.7900000000000003e-14 46.539843264949482 -0 -2.2e-16 -1 -1 3.7300000000000003e-15 -8.2060000000000005e-31 3.7300000000000003e-15 1 -2.2e-16 
1 7.8076372479999995e-08 4.7900000000000003e-14 46.539843264949482 -0 -2.2e-16 -1 -1 3.7300000000000003e-15 -8.2060000000000005e-31 3.7300000000000003e-15 1 -2.2e-16 
1 -30.999999926326073 1.6353000000000001e-13 46.539843264949482 1 -3.7300000000000003e-15 0 -8.2060000000000005e-31 -2.2e-16 -1 3.7300000000000003e-15 1 -2.2e-16 
1 -30.999999926326073 1.6353000000000001e-13 46.539843264949482 1 -3.7300000000000003e-15 0 -8.2060000000000005e-31 -2.2e-16 -1 3.7300000000000003e-15 1 -2.2e-16 
1 -30.999999926326073 1.6353000000000001e-13 46.539843264949482 1 -3.7300000000000003e-15 0 -8.2060000000000005e-31 -2.2e-16 -1 3.7300000000000003e-15 1 -2.2e-16 
1 -30.999999926326073 1.5674999999999999e-13 15.999999746680189 0 2.2e-16 1 1 -3.7300000000000003e-15 8.2060000000000005e-31 3.7300000000000003e-15 1 -2.2e-16 
1 -31.000000000000064 -36.999999999999844 13.999999746680198 0 1 -2.2e-16 1 -0 0 0 -2.2e-16 -1 
1 -31.000000000000064 -36.999999999999844 13.999999746680198 0 1 -2.2e-16 1 -0 0 0 -2.2e-16 -1 
1 -31.000000000000064 -36.999999999999844 13.999999746680198 0 1 -2.2e-16 1 -0 0 0 -2.2e-16 -1 
1 -30.999999926326073 1.5674999999999999e-13 15.999999746680189 0 2.2e-16 1 1 -3.7300000000000003e-15 8.2060000000000005e-31 3.7300000000000003e-15 1 -2.2e-16 
1 -30.999999926326073 1.5674999999999999e-13 15.999999746680189 0 2.2e-16 1 1 -3.7300000000000003e-15 8.2060000000000005e-31 3.7300000000000003e-15 1 -2.2e-16 
1 7.8076372479999995e-08 4.1119999999999999e-14 15.999999746680189 -1 3.7300000000000003e-15 -0 8.2060000000000005e-31 2.2e-16 1 3.7300000000000003e-15 1 -2.2e-16 
1 7.8076372479999995e-08 4.1119999999999999e-14 15.999999746680189 -1 3.7300000000000003e-15 -0 8.2060000000000005e-31 2.2e-16 1 3.7300000000000003e-15 1 -2.2e-16 
1 7.8076372479999995e-08 4.1119999999999999e-14 15.999999746680189 -1 3.7300000000000003e-15 -0 8.2060000000000005e-31 2.2e-16 1 3.7300000000000003e-15 1 -2.2e-16 
2 -1.0999999219236174 5.7100000000000004e-14 69.499999746680203 3.7300000000000003e-15 1 -2.2e-16 -1 3.7300000000000003e-15 0 8.2060000000000005e-31 2.2e-16 1 2.5
2 -1.0999999219236174 5.7100000000000004e-14 69.499999746680203 3.7300000000000003e-15 1 -2.2e-16 -1 3.7300000000000003e-15 0 8.2060000000000005e-31 2.2e-16 1 2.5
2 -1.0999999219236174 5.7100000000000004e-14 69.499999746680203 3.7300000000000003e-15 1 -2.2e-16 -1 3.7300000000000003e-15 0 8.2060000000000005e-31 2.2e-16 1 2.5
1 -1.0999999219236174 5.6550000000000003e-14 66.999999746680203 -0 -2.2e-16 -1 -1 3.7300000000000003e-15 -8.2060000000000005e-31 3.7300000000000003e-15 1 -2.2e-16 
1 -1.0999999219236174 5.6550000000000003e-14 66.999999746680203 -0 -2.2e-16 -1 -1 3.7300000000000003e-15 -8.2060000000000005e-31 3.7300000000000003e-15 1 -2.2e-16 
1 -1.0999999219236174 5.6550000000000003e-14 66.999999746680203 -0 -2.2e-16 -1 -1 3.7300000000000003e-15 -8.2060000000000005e-31 3.7300000000000003e-15 1 -2.2e-16 
2 -29.899999921923612 1.6453000000000001e-13 69.499999746680203 3.7300000000000003e-15 1 -2.2e-16 -1 3.7300000000000003e-15 0 8.2060000000000005e-31 2.2e-16 1 2.5
2 -29.899999921923612 1.6453000000000001e-13 69.499999746680203 3.7300000000000003e-15 1 -2.2e-16 -1 3.7300000000000003e-15 0 8.2060000000000005e-31 2.2e-16 1 2.5
2 -29.899999921923612 1.6453000000000001e-13 69.499999746680203 3.7300000000000003e-15 1 -2.2e-16 -1 3.7300000000000003e-15 0 8.2060000000000005e-31 2.2e-16 1 2.5
1 -32.399999921923609 1.7385000000000001e-13 69.499999746680203 -1 3.7300000000000003e-15 -0 8.2060000000000005e-31 2.2e-16 1 3.7300000000000003e-15 1 -2.2e-16 
1 -32.399999921923609 1.7385000000000001e-13 69.499999746680203 -1 3.7300000000000003e-15 -0 8.2060000000000005e-31 2.2e-16 1 3.7300000000000003e-15 1 -2.2e-16 
1 -32.399999921923609 1.7385000000000001e-13 69.499999746680203 -1 3.7300000000000003e-15 -0 8.2060000000000005e-31 2.2e-16 1 3.7300000000000003e-15 1 -2.2e-16 
1 -32.399999921923609 1.7774000000000001e-13 86.999999746680189 -0.9486832980505141 3.6099999999999999e-15 0.31622776601683711 0.31622776601683711 -9.6999999999999998e-16 0.9486832980505141 3.7314876389986877e-15 1 -2.2135943621178325e-16 
1 -32.399999921923609 1.7774000000000001e-13 86.999999746680189 -0.9486832980505141 3.6099999999999999e-15 0.31622776601683711 0.31622776601683711 -9.6999999999999998e-16 0.9486832980505141 3.7314876389986877e-15 1 -2.2135943621178325e-16 
1 -32.399999921923609 1.7774000000000001e-13 86.999999746680189 -0.9486832980505141 3.6099999999999999e-15 0.31622776601683711 0.31622776601683711 -9.6999999999999998e-16 0.9486832980505141 3.7314876389986877e-15 1 -2.2135943621178325e-16 
2 -28.958481481811358 1.6578999999999999e-13 90.999999746680203 3.7300000000000003e-15 1 -2.2e-16 -1 3.7300000000000003e-15 0 8.2060000000000005e-31 2.2e-16 1 2
2 -28.958481481811358 1.6578999999999999e-13 90.999999746680203 3.7300000000000003e-15 1 -2.2e-16 -1 3.7300000000000003e-15 0 8.2060000000000005e-31 2.2e-16 1 2
2 -28.958481481811358 1.6578999999999999e-13 90.999999746680203 3.7300000000000003e-15 1 -2.2e-16 -1 3.7300000000000003e-15 0 8.2060000000000005e-31 2.2e-16 1 2
1 -2.0415183620358719 6.5829999999999996e-14 92.999999746680203 -0 -2.2e-16 -1 -1 3.7300000000000003e-15 -8.2060000000000005e-31 3.7300000000000003e-15 1 -2.2e-16 
1 -2.0415183620358719 6.5829999999999996e-14 92.999999746680203 -0 -2.2e-16 -1 -1 3.7300000000000003e-15 -8.2060000000000005e-31 3.7300000000000003e-15 1 -2.2e-16 
1 -2.0415183620358719 6.5829999999999996e-14 92.999999746680203 -0 -2.2e-16 -1 -1 3.7300000000000003e-15 -8.2060000000000005e-31 3.7300000000000003e-15 1 -2.2e-16 
2 -2.0415183620358719 6.539e-14 90.999999746680203 3.7300000000000003e-15 1 -2.2e-16 -1 3.7300000000000003e-15 0 8.2060000000000005e-31 2.2e-16 1 2
2 -2.0415183620358719 6.539e-14 90.999999746680203 3.7300000000000003e-15 1 -2.2e-16 -1 3.7300000000000003e-15 0 8.2060000000000005e-31 2.2e-16 1 2
2 -2.0415183620358719 6.539e-14 90.999999746680203 3.7300000000000003e-15 1 -2.2e-16 -1 3.7300000000000003e-15 0 8.2060000000000005e-31 2.2e-16 1 2
1 1.4000000780763826 5.1659999999999998e-14 86.999999746680189 -0.94868329805051399 3.47e-15 -0.31622776601683739 -0.31622776601683739 1.3899999999999999e-15 0.94868329805051399 3.7314876389986877e-15 1 -2.2135943621178858e-16 
1 1.4000000780763826 5.1659999999999998e-14 86.999999746680189 -0.94868329805051399 3.47e-15 -0.31622776601683739 -0.31622776601683739 1.3899999999999999e-15 0.94868329805051399 3.7314876389986877e-15 1 -2.2135943621178858e-16 
1 1.4000000780763826 5.1659999999999998e-14 86.999999746680189 -0.94868329805051399 3.47e-15 -0.31622776601683739 -0.31622776601683739 1.3899999999999999e-15 0.94868329805051399 3.7314876389986877e-15 1 -2.2135943621178858e-16 
1 1.4000000780763826 4.7779999999999999e-14 69.499999746680203 -1 3.7300000000000003e-15 -0 8.2060000000000005e-31 2.2e-16 1 3.7300000000000003e-15 1 -2.2e-16 
1 1.4000000780763826 4.7779999999999999e-14 69.499999746680203 -1 3.7300000000000003e-15 -0 8.2060000000000005e-31 2.2e-16 1 3.7300000000000003e-15 1 -2.2e-16 
1 1.4000000780763826 4.7779999999999999e-14 69.499999746680203 -1 3.7300000000000003e-15 -0 8.2060000000000005e-31 2.2e-16 1 3.7300000000000003e-15 1 -2.2e-16 
1 4.5000000000079394 -15.999999999999964 103.4999997466802 0 2.2e-16 1 -1 3.7499999999999998e-15 -8.2499999999999989e-31 -3.7499999999999998e-15 -1 2.2e-16 
1 -30.999999926326126 -15.999314057492306 13.999999746680192 0 1 -2.2e-16 1 -0 0 0 -2.2e-16 -1 
Triangulations 0

TShapes 248
Ve
1e-07
37.5443269550649 65.9221930860464 0
0 0

0101101
*
Ve
1e-07
37.5443269550649 99.9221930860464 0
0 0

0101101
*
Ed
 1e-07 1 1 0
1  1 0 0 34
2  1 2 6 0 34
2  2 3 6 0 34
2  3 3 8 0 34
2  4 4 8 0 34
2  5 5 8 0 34
2  6 6 11 0 34
2  7 6 13 0 34
2  8 1 14 0 34
2  9 1 16 0 34
2  10 7 14 0 34
0

0101000
+248 0 -247 0 *
Ve
1e-07
-35.3999999219237 -8.99999999999982 86.9999997466802
0 0

0101101
*
Ed
 1e-07 1 1 0
1  2 0 0 9.00000000000001
2  11 1 0 0 9.00000000000001
2  12 8 0 0 9.00000000000001
0

0101000
+247 3 -245 0 *
Ve
1e-07
-35.3999999219237 -8.99999999999982 60.0143259181413
0 0

0101101
*
Ed
 1e-07 1 1 0
1  3 0 -19.6214184571347 7.36425537140417
2  13 1 0 -19.6214184571347 7.36425537140417
2  14 9 17 -19.6214184571347 7.36425537140417
0

0101000
+245 0 -243 0 *
Ve
1e-07
-35.3999999219237 -15.9993140574924 60.0143259181413
0 0

0101101
*
Ed
 1e-07 1 1 0
1  4 0 1 7.99931405749267
2  15 1 0 1 7.99931405749267
2  16 10 0 1 7.99931405749267
0

0101000
+243 0 -241 0 *
Ve
1e-07
-35.3999999219237 -15.9993140574924 52.9999997466802
0 0

0101101
*
Ed
 1e-07 1 1 0
1  5 0 -7.12392417923618 -0.109598007775059
2  17 1 0 -7.12392417923618 -0.109598007775059
2  18 11 0 -7.12392417923618 -0.109598007775059
0

0101000
+241 0 -239 0 *
Ed
 1e-07 1 1 0
1  6 0 0 15.9993140574926
2  19 1 0 0 15.9993140574926
2  20 12 0 0 15.9993140574926
0

0101000
+248 3 -239 0 *
Wi

0101100
-246 3 -244 0 -242 0 -240 0 -238 0 +237 0 *
Fa
0  1e-07 1 0

0111000
+236 0 *
Ve
1e-07
34.9443269550649 65.9221930860464 0
0 0

0101101
*
Ed
 1e-07 1 1 0
1  7 0 0 2.6
2  21 2 6 0 2.6
2  22 13 6 0 2.6
2  23 13 8 0 2.6
2  24 5 8 0 2.6
2  25 14 11 0 2.6
2  26 14 13 0 2.6
2  27 12 14 0 2.6
2  28 12 16 0 2.6
2  29 7 14 0 2.6
0

0101000
+234 0 -248 0 *
Ve
1e-07
34.9443269550649 26.9221930860464 0
0 0

0101101
*
Ed
 1e-07 1 1 0
1  8 0 0 39
2  30 2 6 0 39
2  31 15 6 0 39
2  32 15 8 0 39
2  33 16 11 0 39
2  34 16 13 0 39
2  35 17 14 0 39
2  36 17 16 0 39
2  37 7 14 0 39
0

0101000
+234 0 -232 0 *
Ve
1e-07
0.344326955064859 26.9221930860464 0
0 0

0101101
*
Ed
 1e-07 1 1 0
1  9 0 0 34.6
2  38 2 6 0 34.6
2  39 18 6 0 34.6
2  40 18 8 0 34.6
2  41 19 11 0 34.6
2  42 19 13 0 34.6
2  43 20 14 0 34.6
2  44 20 16 0 34.6
2  45 7 14 0 34.6
0

0101000
+232 0 -230 0 *
Ve
1e-07
0.344326955064859 65.9221930860464 0
0 0

0101101
*
Ed
 1e-07 1 1 0
1  10 0 0 39
2  46 2 6 0 39
2  47 21 6 0 39
2  48 21 8 0 39
2  49 22 11 0 39
2  50 22 13 0 39
2  51 23 14 0 39
2  52 23 16 0 39
2  53 7 14 0 39
0

0101000
+230 0 -228 0 *
Ve
1e-07
-2.25567304493514 65.9221930860464 0
0 0

0101101
*
Ed
 1e-07 1 1 0
1  11 0 0 2.6
2  54 2 6 0 2.6
2  55 24 6 0 2.6
2  56 24 8 0 2.6
2  57 5 8 0 2.6
2  58 25 11 0 2.6
2  59 25 13 0 2.6
2  60 26 14 0 2.6
2  61 26 16 0 2.6
2  62 7 14 0 2.6
0

0101000
+226 0 -228 0 *
Ve
1e-07
-2.25567304493514 99.9221930860464 0
0 0

0101101
*
Ed
 1e-07 1 1 0
1  12 0 0 34
2  63 2 6 0 34
2  64 27 6 0 34
2  65 27 8 0 34
2  66 28 8 0 34
2  67 5 8 0 34
2  68 29 11 0 34
2  69 29 13 0 34
2  70 30 14 0 34
2  71 30 16 0 34
2  72 7 14 0 34
0

0101000
+224 0 -226 0 *
Ve
1.00000043e-07
-0.255673044935141 105.922193086046 0
0 0

0101101
*
Ed
 1e-07 1 1 0
1  13 0 0 6.32455532033677
2  73 2 6 0 6.32455532033677
2  74 31 6 0 6.32455532033677
2  75 31 8 0 6.32455532033677
2  76 5 8 0 6.32455532033677
2  77 32 11 0 6.32455532033677
2  78 32 13 0 6.32455532033677
2  79 33 14 0 6.32455532033677
2  80 33 16 0 6.32455532033677
2  81 7 14 0 6.32455532033677
0

0101000
+224 0 -222 0 *
Ve
1.00000043e-07
-0.255673044935141 116.422193086046 0
0 0

0101101
*
Ed
 1.00000043e-07 1 1 0
1  14 0 0 10.5
2  82 2 6 0 10.5
2  83 34 6 0 10.5
2  84 34 8 0 10.5
2  85 5 8 0 10.5
2  86 35 11 0 10.5
2  87 35 13 0 10.5
2  88 36 14 0 10.5
2  89 36 16 0 10.5
2  90 7 14 0 10.5
0

0101000
+220 0 -222 0 *
Ve
1.00000043e-07
4.74432695506486 116.422193086046 0
0 0

0101101
*
Ed
 1.00000043e-07 1 1 0
1  15 0 0 5
2  91 2 6 0 5
2  92 37 6 0 5
2  93 37 8 0 5
2  94 38 8 0 5
2  95 5 8 0 5
2  96 39 11 0 5
2  97 39 13 0 5
2  98 40 14 0 5
2  99 40 16 0 5
2  100 7 14 0 5
0

0101000
+218 0 -220 0 *
Ve
1.00000043e-07
4.74432695506486 111.422193086046 0
0 0

0101101
*
Ed
 1.00000043e-07 1 1 0
1  16 0 0 5.00000000000001
2  101 2 6 0 5.00000000000001
2  102 41 6 0 5.00000000000001
2  103 41 8 0 5.00000000000001
2  104 5 8 0 5.00000000000001
2  105 42 11 0 5.00000000000001
2  106 42 13 0 5.00000000000001
2  107 43 14 0 5.00000000000001
2  108 43 16 0 5.00000000000001
2  109 7 14 0 5.00000000000001
0

0101000
+216 0 -218 0 *
Ve
1.00000043e-07
6.74432695506486 109.422193086046 0
0 0

0101101
*
Ed
 1.00000043e-07 1 1 0
1  17 0 3.14159265358979 4.71238898038469
2  110 44 6 3.14159265358979 4.71238898038469
2  111 44 8 3.14159265358979 4.71238898038469
2  112 2 6 3.14159265358979 4.71238898038469
2  113 5 8 3.14159265358979 4.71238898038469
2  114 45 11 3.14159265358979 4.71238898038469
2  115 45 13 3.14159265358979 4.71238898038469
2  116 46 14 3.14159265358979 4.71238898038469
2  117 46 16 3.14159265358979 4.71238898038469
2  118 7 14 3.14159265358979 4.71238898038469
0

0101000
+216 0 -214 0 *
Ve
1.00000043e-07
28.5443269550649 109.422193086046 0
0 0

0101101
*
Ed
 1e-07 1 1 0
1  18 0 0 21.8
2  119 2 6 0 21.8
2  120 47 6 0 21.8
2  121 47 8 0 21.8
2  122 5 8 0 21.8
2  123 48 11 0 21.8
2  124 48 13 0 21.8
2  125 49 14 0 21.8
2  126 49 16 0 21.8
2  127 7 14 0 21.8
0

0101000
+212 0 -214 0 *
Ve
1.00000043e-07
30.5443269550649 111.422193086046 0
0 0

0101101
*
Ed
 1.00000043e-07 1 1 0
1  19 0 4.71238898038469 6.28318530717958
2  128 50 6 4.71238898038469 6.28318530717958
2  129 50 8 4.71238898038469 6.28318530717958
2  130 2 6 4.71238898038469 6.28318530717958
2  131 5 8 4.71238898038469 6.28318530717958
2  132 51 11 4.71238898038469 6.28318530717958
2  133 51 13 4.71238898038469 6.28318530717958
2  134 52 14 4.71238898038469 6.28318530717958
2  135 52 16 4.71238898038469 6.28318530717958
2  136 7 14 4.71238898038469 6.28318530717958
0

0101000
+212 0 -210 0 *
Ve
1.00000043e-07
30.5443269550649 116.422193086046 0
0 0

0101101
*
Ed
 1.00000043e-07 1 1 0
1  20 0 0 5.00000000000001
2  137 2 6 0 5.00000000000001
2  138 53 6 0 5.00000000000001
2  139 53 8 0 5.00000000000001
2  140 5 8 0 5.00000000000001
2  141 54 11 0 5.00000000000001
2  142 54 13 0 5.00000000000001
2  143 55 14 0 5.00000000000001
2  144 55 16 0 5.00000000000001
2  145 7 14 0 5.00000000000001
0

0101000
+208 0 -210 0 *
Ve
1.00000043e-07
35.5443269550649 116.422193086046 0
0 0

0101101
*
Ed
 1.00000043e-07 1 1 0
1  21 0 0 5
2  146 2 6 0 5
2  147 56 6 0 5
2  148 56 8 0 5
2  149 38 8 0 5
2  150 5 8 0 5
2  151 57 11 0 5
2  152 57 13 0 5
2  153 58 14 0 5
2  154 58 16 0 5
2  155 7 14 0 5
0

0101000
+206 0 -208 0 *
Ve
1.00000043e-07
35.5443269550649 105.922193086046 0
0 0

0101101
*
Ed
 1.00000043e-07 1 1 0
1  22 0 0 10.5
2  156 2 6 0 10.5
2  157 59 6 0 10.5
2  158 59 8 0 10.5
2  159 5 8 0 10.5
2  160 60 11 0 10.5
2  161 60 13 0 10.5
2  162 61 14 0 10.5
2  163 61 16 0 10.5
2  164 7 14 0 10.5
0

0101000
+204 0 -206 0 *
Ed
 1e-07 1 1 0
1  23 0 0 6.32455532033677
2  165 2 6 0 6.32455532033677
2  166 62 6 0 6.32455532033677
2  167 62 8 0 6.32455532033677
2  168 5 8 0 6.32455532033677
2  169 63 11 0 6.32455532033677
2  170 63 13 0 6.32455532033677
2  171 8 14 0 6.32455532033677
2  172 8 16 0 6.32455532033677
2  173 7 14 0 6.32455532033677
0

0101000
+247 0 -204 0 *
Wi

0101100
-246 0 -233 0 +231 0 +229 0 +227 0 -225 0 -223 0 +221 0 -219 0 -217 0 
-215 0 +213 0 -211 0 +209 0 -207 0 -205 0 -203 0 -202 0 *
Ve
1e-07
2.14432695506487 59.4620366043157 0
0 0

0101101
*
Ve
1e-07
33.1443269594673 59.4620366043157 0
0 0

0101101
*
Ed
 1e-07 1 1 0
1  24 0 0 31.0000000044024
2  174 2 6 0 31.0000000044024
2  175 64 6 0 31.0000000044024
2  176 64 8 0 31.0000000044024
2  177 5 8 0 31.0000000044024
2  178 65 11 0 31.0000000044024
2  179 65 13 0 31.0000000044024
2  180 66 14 0 31.0000000044024
2  181 66 16 0 31.0000000044024
2  182 7 14 0 31.0000000044024
0

0101000
+200 0 -199 0 *
Ve
1e-07
33.1443269594673 28.9221930860464 0
0 0

0101101
*
Ed
 1e-07 1 1 0
1  25 0 0 30.5398435182693
2  183 2 6 0 30.5398435182693
2  184 67 6 0 30.5398435182693
2  185 67 8 0 30.5398435182693
2  186 68 11 0 30.5398435182693
2  187 68 13 0 30.5398435182693
2  188 69 14 0 30.5398435182693
2  189 69 16 0 30.5398435182693
2  190 7 14 0 30.5398435182693
0

0101000
+199 0 -197 0 *
Ve
1.78076338e-07
2.14432695506487 28.9221930860464 0
0 0

0101101
*
Ed
 1.00000107e-07 1 1 0
1  26 0 0 31.0000000044024
2  191 2 6 0 31.0000000044024
2  192 70 6 0 31.0000000044024
2  193 70 8 0 31.0000000044024
2  194 71 8 0 31.0000000044024
2  195 72 8 0 31.0000000044024
2  196 73 8 0 31.0000000044024
2  197 74 11 0 31.0000000044024
2  198 74 13 0 31.0000000044024
2  199 75 14 0 31.0000000044024
2  200 75 16 0 31.0000000044024
2  201 7 14 0 31.0000000044024
0

0101000
+197 0 -195 0 *
Ed
 1.00000107e-07 1 1 0
1  27 0 0 30.5398435182693
2  202 2 6 0 30.5398435182693
2  203 76 6 0 30.5398435182693
2  204 76 8 0 30.5398435182693
2  205 77 11 0 30.5398435182693
2  206 77 13 0 30.5398435182693
2  207 78 14 0 30.5398435182693
2  208 78 16 0 30.5398435182693
2  209 7 14 0 30.5398435182693
0

0101000
+195 0 -200 0 *
Wi

0101100
+198 0 +196 0 +194 0 +193 0 *
Ve
1e-07
0.744326955064859 82.4221930860464 0
0 0

0101101
*
Ve
1.00000014e-07
3.24432695506486 79.9221930860464 0
0 0

0101101
*
Ed
 1e-07 1 1 0
1  28 0 3.14159265358979 4.71238898038469
2  210 79 6 3.14159265358979 4.71238898038469
2  211 79 8 3.14159265358979 4.71238898038469
2  212 2 6 3.14159265358979 4.71238898038469
2  213 5 8 3.14159265358979 4.71238898038469
2  214 80 11 3.14159265358979 4.71238898038469
2  215 80 13 3.14159265358979 4.71238898038469
2  216 81 14 3.14159265358979 4.71238898038469
2  217 81 16 3.14159265358979 4.71238898038469
2  218 7 14 3.14159265358979 4.71238898038469
0

0101000
+191 0 -190 0 *
Ve
1.00000014e-07
32.0443269550649 79.9221930860464 0
0 0

0101101
*
Ed
 1.00000014e-07 1 1 0
1  29 0 0 28.8
2  219 2 6 0 28.8
2  220 82 6 0 28.8
2  221 82 8 0 28.8
2  222 5 8 0 28.8
2  223 83 11 0 28.8
2  224 83 13 0 28.8
2  225 84 14 0 28.8
2  226 84 16 0 28.8
2  227 7 14 0 28.8
0

0101000
+190 0 -188 0 *
Ve
1e-07
34.5443269550649 82.4221930860464 0
0 0

0101101
*
Ed
 1e-07 1 1 0
1  30 0 4.71238898038469 6.28318530717958
2  228 85 6 4.71238898038469 6.28318530717958
2  229 85 8 4.71238898038469 6.28318530717958
2  230 2 6 4.71238898038469 6.28318530717958
2  231 5 8 4.71238898038469 6.28318530717958
2  232 86 11 4.71238898038469 6.28318530717958
2  233 86 13 4.71238898038469 6.28318530717958
2  234 87 14 4.71238898038469 6.28318530717958
2  235 87 16 4.71238898038469 6.28318530717958
2  236 7 14 4.71238898038469 6.28318530717958
0

0101000
+188 0 -186 0 *
Ve
1e-07
34.5443269550649 99.9221930860464 0
0 0

0101101
*
Ed
 1e-07 1 1 0
1  31 0 0 17.5
2  237 2 6 0 17.5
2  238 88 6 0 17.5
2  239 88 8 0 17.5
2  240 5 8 0 17.5
2  241 89 11 0 17.5
2  242 89 13 0 17.5
2  243 90 14 0 17.5
2  244 90 16 0 17.5
2  245 7 14 0 17.5
0

0101000
+186 0 -184 0 *
Ve
1e-07
33.0001751110536 104.55464861808 0
0 0

0101101
*
Ed
 1e-07 1 1 0
1  32 0 0 4.88303688022452
2  246 2 6 0 4.88303688022452
2  247 91 6 0 4.88303688022452
2  248 91 8 0 4.88303688022452
2  249 5 8 0 4.88303688022452
2  250 92 11 0 4.88303688022452
2  251 92 13 0 4.88303688022452
2  252 93 14 0 4.88303688022452
2  253 93 16 0 4.88303688022452
2  254 7 14 0 4.88303688022452
0

0101000
+184 0 -182 0 *
Ve
1e-07
31.1028085149526 105.922193086046 0
0 0

0101101
*
Ed
 1e-07 1 1 0
1  33 0 0.32175055439664 1.5707963267949
2  255 94 6 0.32175055439664 1.5707963267949
2  256 94 8 0.32175055439664 1.5707963267949
2  257 2 6 0.32175055439664 1.5707963267949
2  258 5 8 0.32175055439664 1.5707963267949
2  259 95 11 0.32175055439664 1.5707963267949
2  260 95 13 0.32175055439664 1.5707963267949
2  261 96 14 0.32175055439664 1.5707963267949
2  262 96 16 0.32175055439664 1.5707963267949
2  263 7 14 0.32175055439664 1.5707963267949
0

0101000
+182 0 -180 0 *
Ve
1e-07
4.18584539517711 105.922193086046 0
0 0

0101101
*
Ed
 1e-07 1 1 0
1  34 0 0 26.9169631197755
2  264 2 6 0 26.9169631197755
2  265 97 6 0 26.9169631197755
2  266 97 8 0 26.9169631197755
2  267 5 8 0 26.9169631197755
2  268 98 11 0 26.9169631197755
2  269 98 13 0 26.9169631197755
2  270 99 14 0 26.9169631197755
2  271 99 16 0 26.9169631197755
2  272 7 14 0 26.9169631197755
0

0101000
+178 0 -180 0 *
Ve
1e-07
2.28847879907609 104.55464861808 0
0 0

0101101
*
Ed
 1e-07 1 1 0
1  35 0 1.5707963267949 2.81984209919315
2  273 100 6 1.5707963267949 2.81984209919315
2  274 100 8 1.5707963267949 2.81984209919315
2  275 2 6 1.5707963267949 2.81984209919315
2  276 5 8 1.5707963267949 2.81984209919315
2  277 101 11 1.5707963267949 2.81984209919315
2  278 101 13 1.5707963267949 2.81984209919315
2  279 102 14 1.5707963267949 2.81984209919315
2  280 102 16 1.5707963267949 2.81984209919315
2  281 7 14 1.5707963267949 2.81984209919315
0

0101000
+178 0 -176 0 *
Ve
1e-07
0.744326955064859 99.9221930860464 0
0 0

0101101
*
Ed
 1e-07 1 1 0
1  36 0 0 4.88303688022452
2  282 2 6 0 4.88303688022452
2  283 103 6 0 4.88303688022452
2  284 103 8 0 4.88303688022452
2  285 5 8 0 4.88303688022452
2  286 104 11 0 4.88303688022452
2  287 104 13 0 4.88303688022452
2  288 105 14 0 4.88303688022452
2  289 105 16 0 4.88303688022452
2  290 7 14 0 4.88303688022452
0

0101000
+174 0 -176 0 *
Ed
 1e-07 1 1 0
1  37 0 0 17.5
2  291 2 6 0 17.5
2  292 106 6 0 17.5
2  293 106 8 0 17.5
2  294 5 8 0 17.5
2  295 107 11 0 17.5
2  296 107 13 0 17.5
2  297 108 14 0 17.5
2  298 108 16 0 17.5
2  299 7 14 0 17.5
0

0101000
+191 0 -174 0 *
Wi

0101100
+189 0 +187 0 +185 0 +183 0 +181 0 +179 0 -177 0 +175 0 -173 0 -172 0 
*
Fa
0  1e-07 7 0

0111000
-201 3 +192 3 -171 3 *
Ve
1.00000043e-07
-33.3999999219237 -8.99999999999983 92.9999997466802
0 0

0101101
*
Ed
 1.00000043e-07 1 1 0
1  38 0 0 9.00000000000001
2  300 61 0 0 9.00000000000001
2  301 8 0 0 9.00000000000001
0

0101000
+204 3 -169 0 *
Ed
 1e-07 1 1 0
1  39 0 -5.66498496829799 0.659570352038786
2  302 8 0 -5.66498496829799 0.659570352038786
2  303 9 17 -5.66498496829799 0.659570352038786
0

0101000
+169 0 -245 0 *
Wi

0101100
-202 3 -168 0 -167 0 +244 0 *
Fa
0  1e-07 8 0

0111000
+166 0 *
Ve
1.00000043e-07
2.40000007807635 -8.99999999999996 103.49999974668
0 0

0101101
*
Ve
1.00000043e-07
-2.59999992192365 -8.99999999999994 103.49999974668
0 0

0101101
*
Ed
 1.00000043e-07 1 1 0
1  40 0 2.09999992193162 7.09999992193162
2  304 109 21 2.09999992193162 7.09999992193162
2  305 109 22 2.09999992193162 7.09999992193162
2  306 9 21 2.09999992193162 7.09999992193162
2  307 40 22 2.09999992193162 7.09999992193162
0

0101000
+164 22 -163 22 *
Ve
1.00000043e-07
-2.59999992192365 -8.99999999999994 98.4999997466802
0 0

0101101
*
Ed
 1.00000043e-07 1 1 0
1  41 0 -13.3714184571347 -8.37141845713471
2  308 43 0 -13.3714184571347 -8.37141845713471
2  309 9 17 -13.3714184571347 -8.37141845713471
0

0101000
+163 0 -161 0 *
Ve
1.00000043e-07
-4.59999992192365 -8.99999999999993 96.4999997466802
0 0

0101101
*
Ed
 1.00000043e-07 1 1 0
1  42 0 3.14159265358979 4.71238898038469
2  310 46 0 3.14159265358979 4.71238898038469
2  311 9 17 3.14159265358979 4.71238898038469
0

0101000
+161 0 -159 0 *
Ve
1.00000043e-07
-26.3999999219237 -8.99999999999985 96.4999997466802
0 0

0101101
*
Ed
 1e-07 1 1 0
1  43 0 -16.3500000390342 5.44999996096581
2  312 49 0 -16.3500000390342 5.44999996096581
2  313 9 17 -16.3500000390342 5.44999996096581
0

0101000
+159 0 -157 0 *
Ve
1.00000043e-07
-28.3999999219237 -8.99999999999985 98.4999997466802
0 0

0101101
*
Ed
 1.00000043e-07 1 1 0
1  44 0 4.71238898038469 6.28318530717959
2  314 52 0 4.71238898038469 6.28318530717959
2  315 9 17 4.71238898038469 6.28318530717959
0

0101000
+157 0 -155 0 *
Ve
1.00000043e-07
-28.3999999219237 -8.99999999999984 103.49999974668
0 0

0101101
*
Ed
 1.00000043e-07 1 1 0
1  45 0 5.87141845713471 10.8714184571347
2  316 55 0 5.87141845713471 10.8714184571347
2  317 9 17 5.87141845713471 10.8714184571347
0

0101000
+155 0 -153 0 *
Ve
1.00000043e-07
-33.3999999219237 -8.99999999999982 103.49999974668
0 0

0101101
*
Ed
 1.00000043e-07 1 1 0
1  40 0 32.8999999219316 37.8999999219316
2  304 109 21 32.8999999219316 37.8999999219316
2  305 109 22 32.8999999219316 37.8999999219316
2  306 9 21 32.8999999219316 37.8999999219316
2  318 58 22 32.8999999219316 37.8999999219316
0

0101000
+153 22 -151 22 *
Ed
 1.00000043e-07 1 1 0
1  46 0 -16.1214184571347 -5.62141845713472
2  319 61 0 -16.1214184571347 -5.62141845713472
2  320 9 17 -16.1214184571347 -5.62141845713472
0

0101000
+151 0 -169 0 *
Ve
1e-07
4.40000007807635 -8.99999999999997 60.0143259181413
0 0

0101101
*
Ed
 1e-07 1 1 0
1  47 0 0.100000078068376 39.9000000780684
2  321 9 21 0.100000078068376 39.9000000780684
2  322 10 21 0.100000078068376 39.9000000780684
2  323 10 22 0.100000078068376 39.9000000780684
0

0101000
+243 22 -148 22 *
Ve
1e-07
4.40000007807635 -8.99999999999997 86.9999997466802
0 0

0101101
*
Ed
 1e-07 1 1 0
1  48 0 -24.3642553714042 2.62141845713471
2  324 30 0 -24.3642553714042 2.62141845713471
2  325 9 17 -24.3642553714042 2.62141845713471
0

0101000
+148 0 -146 0 *
Ve
1.00000043e-07
2.40000007807635 -8.99999999999996 92.9999997466802
0 0

0101101
*
Ed
 1e-07 1 1 0
1  49 0 -5.6649849436106 0.659570376726171
2  326 33 0 -5.6649849436106 0.659570376726171
2  327 9 17 -5.6649849436106 0.659570376726171
0

0101000
+144 0 -146 0 *
Ed
 1.00000043e-07 1 1 0
1  50 0 0.371418457134723 10.8714184571347
2  328 36 0 0.371418457134723 10.8714184571347
2  329 9 17 0.371418457134723 10.8714184571347
0

0101000
+144 0 -164 0 *
Wi

0101100
-162 20 -160 0 -158 0 -156 0 -154 0 -152 0 -150 20 -149 0 -167 0 -242 0 
-147 20 -145 0 +143 0 -142 0 *
Ve
1e-07
1.40000007807635 -8.99999999999996 69.4999997466802
0 0

0101101
*
Ve
1.50000014e-07
-1.09999992192365 -8.99999999999995 66.9999997466802
0 0

0101101
*
Ed
 1e-07 1 1 0
1  51 0 3.14159265358979 4.71238898038469
2  330 81 0 3.14159265358979 4.71238898038469
2  331 9 17 3.14159265358979 4.71238898038469
0

0101000
+140 0 -139 0 *
Ve
1.50000014e-07
-29.8999999219236 -8.99999999999985 66.9999997466802
0 0

0101101
*
Ed
 1.50000014e-07 1 1 0
1  52 0 -21.5999999609658 7.20000003903419
2  332 84 0 -21.5999999609658 7.20000003903419
2  333 9 17 -21.5999999609658 7.20000003903419
0

0101000
+137 0 -139 0 *
Ve
1e-07
-32.3999999219236 -8.99999999999984 69.4999997466802
0 0

0101101
*
Ed
 1e-07 1 1 0
1  53 0 4.71238898038469 6.28318530717959
2  334 87 0 4.71238898038469 6.28318530717959
2  335 9 17 4.71238898038469 6.28318530717959
0

0101000
+137 0 -135 0 *
Ve
1e-07
-32.3999999219236 -8.99999999999983 86.9999997466802
0 0

0101101
*
Ed
 1e-07 1 1 0
1  54 0 -11.3714184571347 6.12858154286528
2  336 90 0 -11.3714184571347 6.12858154286528
2  337 9 17 -11.3714184571347 6.12858154286528
0

0101000
+133 0 -135 0 *
Ve
1e-07
-30.8558480779124 -8.99999999999984 91.6324552787139
0 0

0101101
*
Ed
 1e-07 1 1 0
1  55 0 -4.69780817721099 0.185228703013525
2  338 93 0 -4.69780817721099 0.185228703013525
2  339 9 17 -4.69780817721099 0.185228703013525
0

0101000
+131 0 -133 0 *
Ve
1e-07
-28.9584814818114 -8.99999999999984 92.9999997466802
0 0

0101101
*
Ed
 1e-07 1 1 0
1  56 0 0.321750554396641 1.5707963267949
2  340 96 0 0.321750554396641 1.5707963267949
2  341 9 17 0.321750554396641 1.5707963267949
0

0101000
+131 0 -129 0 *
Ve
1e-07
-2.04151836203591 -8.99999999999994 92.9999997466802
0 0

0101101
*
Ed
 1e-07 1 1 0
1  57 0 -20.1877223007974 6.72924081897806
2  342 99 0 -20.1877223007974 6.72924081897806
2  343 9 17 -20.1877223007974 6.72924081897806
0

0101000
+129 0 -127 0 *
Ve
1e-07
-0.144151765934877 -8.99999999999995 91.6324552787139
0 0

0101101
*
Ed
 1e-07 1 1 0
1  58 0 1.5707963267949 2.81984209919315
2  344 102 0 1.5707963267949 2.81984209919315
2  345 9 17 1.5707963267949 2.81984209919315
0

0101000
+127 0 -125 0 *
Ve
1e-07
1.40000007807635 -8.99999999999996 86.9999997466802
0 0

0101101
*
Ed
 1e-07 1 1 0
1  59 0 -4.69780815252359 0.185228727700927
2  346 105 0 -4.69780815252359 0.185228727700927
2  347 9 17 -4.69780815252359 0.185228727700927
0

0101000
+125 0 -123 0 *
Ed
 1e-07 1 1 0
1  60 0 -11.3714184571347 6.12858154286528
2  348 108 0 -11.3714184571347 6.12858154286528
2  349 9 17 -11.3714184571347 6.12858154286528
0

0101000
+123 0 -140 0 *
Wi

0101100
-138 0 +136 0 -134 0 +132 0 +130 0 -128 0 -126 0 -124 0 -122 0 -121 0 
*
Fa
0  1e-07 9 17

0111000
+141 0 +120 0 *
Ve
1e-07
4.40000007807632 -15.9993140574924 60.0143259181413
0 0

0101101
*
Ed
 1.5e-07 1 1 0
1  61 0 -29.8990265420786 9.90097345792141
2  350 11 0 -29.8990265420786 9.90097345792141
2  351 10 0 -29.8990265420786 9.90097345792141
0

0101000
+118 0 -241 0 *
Ed
 1e-07 1 1 0
1  62 0 -7.99931405749253 -1
2  352 30 0 -7.99931405749253 -1
2  353 10 0 -7.99931405749253 -1
0

0101000
+118 0 -148 0 *
Wi

0101100
-240 0 +117 0 -116 0 +147 20 *
Fa
0  1e-07 10 0

0111000
+115 0 *
Ve
1e-07
-32.7999999219237 -15.9993140574924 52.9999997466802
0 0

0101101
*
Ed
 1e-07 1 1 0
1  63 0 -11.2509734969556 -8.65097349695562
2  354 12 0 -11.2509734969556 -8.65097349695562
2  355 11 0 -11.2509734969556 -8.65097349695562
0

0101000
+239 0 -113 0 *
Ve
1e-07
-32.7999999219237 -15.9993140574923 13.9999997466802
0 0

0101101
*
Ed
 1e-07 1 1 0
1  64 0 -38.8904019922249 0.109598007775064
2  356 17 0 -38.8904019922249 0.109598007775064
2  357 11 0 -38.8904019922249 0.109598007775064
0

0101000
+111 0 -113 0 *
Ve
1e-07
1.80000007807632 -15.9993140574923 13.9999997466802
0 0

0101101
*
Ed
 1e-07 1 1 0
1  65 0 -25.9490265030444 8.65097349695562
2  358 20 0 -25.9490265030444 8.65097349695562
2  359 11 0 -25.9490265030444 8.65097349695562
0

0101000
+109 0 -111 0 *
Ve
1e-07
1.80000007807632 -15.9993140574924 52.9999997466802
0 0

0101101
*
Ed
 1e-07 1 1 0
1  66 0 -19.6095980077751 19.3904019922249
2  360 23 0 -19.6095980077751 19.3904019922249
2  361 11 0 -19.6095980077751 19.3904019922249
0

0101000
+107 0 -109 0 *
Ve
1e-07
4.40000007807632 -15.9993140574924 52.9999997466802
0 0

0101101
*
Ed
 1e-07 1 1 0
1  67 0 7.34902650304438 9.94902650304438
2  362 26 0 7.34902650304438 9.94902650304438
2  363 11 0 7.34902650304438 9.94902650304438
0

0101000
+107 0 -105 0 *
Ed
 1e-07 1 1 0
1  68 0 -16.8904019922249 -9.87607582076381
2  364 30 0 -16.8904019922249 -9.87607582076381
2  365 11 0 -16.8904019922249 -9.87607582076381
0

0101000
+105 0 -118 0 *
Wi

0101100
-238 0 -112 0 +110 0 +108 0 +106 0 -104 0 -103 0 -117 0 *
Ve
1e-07
-30.9999999263261 -15.9993140574924 46.5398432649495
0 0

0101101
*
Ve
1e-07
7.8076313e-08 -15.9993140574924 46.5398432649495
0 0

0101101
*
Ed
 1e-07 1 1 0
1  69 0 -23.2509735013581 7.74902650304438
2  366 66 0 -23.2509735013581 7.74902650304438
2  367 11 0 -23.2509735013581 7.74902650304438
0

0101000
+101 0 -100 0 *
Ve
1.00000018e-07
-30.9999999263261 -15.9993140574923 15.9999997466802
0 0

0101101
*
Ed
 1e-07 1 1 0
1  70 0 -33.6603237513596 -3.12048023309029
2  368 69 0 -33.6603237513596 -3.12048023309029
2  369 11 0 -33.6603237513596 -3.12048023309029
0

0101000
+98 0 -101 0 *
Ve
1.00000032e-07
7.8076313e-08 -15.9993140574923 15.9999997466802
0 0

0101101
*
Ed
 1e-07 1 1 0
1  71 0 -12.1494415260444 18.3904019922249
2  370 78 0 -12.1494415260444 18.3904019922249
2  371 11 0 -12.1494415260444 18.3904019922249
0

0101000
+100 0 -96 0 *
Ed
 1.00000009e-07 1 1 0
1  72 0 -23.2490265052456 7.75097349915684
2  372 75 0 -23.2490265052456 7.75097349915684
2  373 11 0 -23.2490265052456 7.75097349915684
2  374 110 30 -23.2490265052456 7.75097349915684
0

0101000
+96 0 -98 0 *
Wi

0101100
-99 0 -97 0 -95 0 -94 0 *
Fa
0  1e-07 11 0

0111000
+102 0 +93 0 *
Ed
 1e-07 1 1 0
1  73 0 0 15.9993140574926
2  375 12 0 0 15.9993140574926
2  376 17 0 0 15.9993140574926
0

0101000
+234 3 -113 0 *
Wi

0101100
-233 3 -237 0 -112 0 +91 0 *
Fa
0  1e-07 12 0

0111000
+90 0 *
Ed
 1e-07 1 1 0
1  74 0 0 15.9993140574925
2  377 17 0 0 15.9993140574925
2  378 20 0 0 15.9993140574925
0

0101000
+232 3 -111 0 *
Wi

0101100
-231 3 -88 0 -110 0 +91 0 *
Fa
0  1e-07 17 0

0111000
+87 0 *
Ed
 1e-07 1 1 0
1  75 0 0 15.9993140574923
2  379 20 0 0 15.9993140574923
2  380 23 0 0 15.9993140574923
0

0101000
+230 3 -109 0 *
Wi

0101100
-229 3 -85 0 -108 0 +88 0 *
Fa
0  1e-07 20 0

0111000
+84 0 *
Ed
 1e-07 1 1 0
1  76 0 0 15.9993140574924
2  381 23 0 0 15.9993140574924
2  382 26 0 0 15.9993140574924
0

0101000
+228 3 -107 0 *
Wi

0101100
-227 3 -82 0 -106 0 +85 0 *
Fa
0  1e-07 23 0

0111000
+81 0 *
Ed
 1e-07 1 1 0
1  77 0 0 15.9993140574924
2  383 26 0 0 15.9993140574924
2  384 30 0 0 15.9993140574924
0

0101000
+226 3 -105 0 *
Wi

0101100
-225 3 -82 0 -104 0 +79 0 *
Fa
0  1e-07 26 0

0111000
+78 0 *
Ed
 1e-07 1 1 0
1  78 0 0 9.00000000000001
2  385 30 0 0 9.00000000000001
2  386 33 0 0 9.00000000000001
0

0101000
+224 3 -146 0 *
Wi

0101100
-223 3 -79 0 -103 0 -116 0 -145 0 +76 0 *
Fa
0  1.00000043e-07 30 0

0111000
+75 0 *
Ed
 1.00000043e-07 1 1 0
1  79 0 0 9.00000000000001
2  387 33 0 0 9.00000000000001
2  388 36 0 0 9.00000000000001
0

0101000
+222 3 -144 0 *
Wi

0101100
-221 3 -73 0 -143 0 +76 0 *
Fa
0  1e-07 33 0

0111000
+72 0 *
Ed
 1.00000043e-07 1 1 0
1  80 0 0 9.00000000000001
2  389 36 0 0 9.00000000000001
2  390 40 0 0 9.00000000000001
0

0101000
+220 3 -164 0 *
Wi

0101100
-219 3 -73 0 -142 0 +70 0 *
Fa
0  1.00000043e-07 36 0

0111000
+69 0 *
Ed
 1.00000043e-07 1 1 0
1  81 0 0 9.00000000000001
2  391 40 0 0 9.00000000000001
2  392 43 0 0 9.00000000000001
0

0101000
+218 3 -163 0 *
Wi

0101100
-217 3 -70 0 -162 20 +67 0 *
Fa
0  1.00000043e-07 40 0

0111000
+66 0 *
Ed
 1.00000043e-07 1 1 0
1  82 0 0 9.00000000000001
2  393 46 0 0 9.00000000000001
4 G1 43 0 46 0
2  394 43 0 0 9.00000000000001
0

0101000
+216 3 -161 0 *
Wi

0101100
-215 3 -67 0 -160 0 +64 0 *
Fa
0  1.00000043e-07 43 0

0111000
+63 0 *
Ed
 1.00000043e-07 1 1 0
1  83 0 0 9.00000000000001
2  395 46 0 0 9.00000000000001
4 G1 46 0 49 0
2  396 49 0 0 9.00000000000001
0

0101000
+214 3 -159 0 *
Wi

0101100
-213 3 -61 0 +158 0 +64 0 *
Fa
0  1.00000043e-07 46 0

0111000
+60 0 *
Ed
 1.00000043e-07 1 1 0
1  84 0 0 9.00000000000001
2  397 52 0 0 9.00000000000001
4 G1 49 0 52 0
2  398 49 0 0 9.00000000000001
0

0101000
+212 3 -157 0 *
Wi

0101100
-211 3 -61 0 -156 0 +58 0 *
Fa
0  1e-07 49 0

0111000
+57 0 *
Ed
 1.00000043e-07 1 1 0
1  85 0 0 9.00000000000001
2  399 52 0 0 9.00000000000001
4 G1 52 0 55 0
2  400 55 0 0 9.00000000000001
0

0101000
+210 3 -155 0 *
Wi

0101100
-209 3 -55 0 +154 0 +58 0 *
Fa
0  1.00000043e-07 52 0

0111000
+54 0 *
Ed
 1.00000043e-07 1 1 0
1  86 0 0 9.00000000000001
2  401 55 0 0 9.00000000000001
2  402 58 0 0 9.00000000000001
0

0101000
+208 3 -153 0 *
Wi

0101100
-207 3 -55 0 -152 0 +52 0 *
Fa
0  1.00000043e-07 55 0

0111000
+51 0 *
Ed
 1.00000043e-07 1 1 0
1  87 0 0 9.00000000000001
2  403 58 0 0 9.00000000000001
2  404 61 0 0 9.00000000000001
0

0101000
+206 3 -151 0 *
Wi

0101100
-205 3 -52 0 -150 20 +49 0 *
Fa
0  1.00000043e-07 58 0

0111000
+48 0 *
Wi

0101100
-203 3 -49 0 -149 0 +168 0 *
Fa
0  1.00000043e-07 61 0

0111000
+46 0 *
Ed
 1.00000107e-07 1 1 0
1  88 0 0 15.9993140574925
2  405 66 0 0 15.9993140574925
2  406 69 0 0 15.9993140574925
0

0101000
+199 3 -101 0 *
Ed
 1e-07 1 1 0
1  89 0 0 15.9993140574924
2  407 66 0 0 15.9993140574924
2  408 78 0 0 15.9993140574924
0

0101000
+200 3 -100 0 *
Wi

0101100
-198 3 -44 0 -99 0 +43 0 *
Fa
0  1.00000107e-07 66 0

0111000
+42 0 *
Ed
 1.73673945e-07 1 1 0
1  90 0 0 15.9993140574925
2  409 69 0 0 15.9993140574925
2  410 75 0 0 15.9993140574925
0

0101000
+197 3 -98 0 *
Wi

0101100
-196 3 -40 0 -97 0 +44 0 *
Fa
0  1.00000107e-07 69 0

0111000
+39 0 *
Ed
 1.78076338e-07 1 1 0
1  91 0 0 15.9993140574924
2  411 75 0 0 15.9993140574924
2  412 78 0 0 15.9993140574924
0

0101000
+195 3 -96 0 *
Wi

0101100
-194 3 -37 0 -94 0 +40 0 *
Fa
0  1.00000107e-07 75 0

0111000
+36 0 *
Wi

0101100
-193 3 -43 0 -95 0 +37 0 *
Fa
0  1.00000107e-07 78 0

0111000
+34 0 *
Ed
 1.00000014e-07 1 1 0
1  92 0 0 9.00000000000001
2  413 81 0 0 9.00000000000001
4 G1 81 0 84 0
2  414 84 0 0 9.00000000000001
0

0101000
+190 3 -139 0 *
Ed
 1e-07 1 1 0
1  93 0 0 9.00000000000001
2  415 81 0 0 9.00000000000001
4 G1 81 0 108 0
2  416 108 0 0 9.00000000000001
0

0101000
+191 3 -140 0 *
Wi

0101100
-189 3 -32 0 +138 0 +31 0 *
Fa
0  1e-07 81 0

0111000
+30 0 *
Ed
 1.00000014e-07 1 1 0
1  94 0 0 9.00000000000001
2  417 87 0 0 9.00000000000001
4 G1 84 0 87 0
2  418 84 0 0 9.00000000000001
0

0101000
+188 3 -137 0 *
Wi

0101100
-187 3 -28 0 -136 0 +32 0 *
Fa
0  1.00000014e-07 84 0

0111000
+27 0 *
Ed
 1e-07 1 1 0
1  95 0 0 9.00000000000001
2  419 87 0 0 9.00000000000001
4 G1 87 0 90 0
2  420 90 0 0 9.00000000000001
0

0101000
+186 3 -135 0 *
Wi

0101100
-185 3 -25 0 +134 0 +28 0 *
Fa
0  1e-07 87 0

0111000
+24 0 *
Ed
 1e-07 1 1 0
1  96 0 0 9.00000000000001
2  421 90 0 0 9.00000000000001
2  422 93 0 0 9.00000000000001
0

0101000
+184 3 -133 0 *
Wi

0101100
-183 3 -22 0 -132 0 +25 0 *
Fa
0  1e-07 90 0

0111000
+21 0 *
Ed
 1e-07 1 1 0
1  97 0 0 9.00000000000001
2  423 96 0 0 9.00000000000001
4 G1 93 0 96 0
2  424 93 0 0 9.00000000000001
0

0101000
+182 3 -131 0 *
Wi

0101100
-181 3 -19 0 -130 0 +22 0 *
Fa
0  1e-07 93 0

0111000
+18 0 *
Ed
 1e-07 1 1 0
1  98 0 0 9.00000000000001
2  425 96 0 0 9.00000000000001
4 G1 96 0 99 0
2  426 99 0 0 9.00000000000001
0

0101000
+180 3 -129 0 *
Wi

0101100
-179 3 -16 0 +128 0 +19 0 *
Fa
0  1e-07 96 0

0111000
+15 0 *
Ed
 1e-07 1 1 0
1  99 0 0 9.00000000000001
2  427 102 0 0 9.00000000000001
4 G1 99 0 102 0
2  428 99 0 0 9.00000000000001
0

0101000
+178 3 -127 0 *
Wi

0101100
-177 3 -16 0 -126 0 +13 0 *
Fa
0  1e-07 99 0

0111000
+12 0 *
Ed
 1e-07 1 1 0
1  100 0 0 9.00000000000001
2  429 102 0 0 9.00000000000001
4 G1 102 0 105 0
2  430 105 0 0 9.00000000000001
0

0101000
+176 3 -125 0 *
Wi

0101100
-175 3 -10 0 +124 0 +13 0 *
Fa
0  1e-07 102 0

0111000
+9 0 *
Ed
 1e-07 1 1 0
1  101 0 0 9.00000000000001
2  431 105 0 0 9.00000000000001
2  432 108 0 0 9.00000000000001
0

0101000
+174 3 -123 0 *
Wi

0101100
-173 3 -10 0 -122 0 +7 0 *
Fa
0  1e-07 105 0

0111000
+6 0 *
Wi

0101100
-172 3 -7 0 -121 0 +31 0 *
Fa
0  1e-07 108 0

0111000
+4 0 *
Sh

0101100
+235 0 +170 0 +165 0 -119 0 -114 0 -92 0 +89 0 -86 0 -83 0 -80 0 
+77 0 +74 0 -71 0 +68 0 +65 0 +62 0 -59 0 +56 0 -53 0 +50 0 
+47 0 +45 0 +41 0 +38 0 +35 0 +33 0 -29 0 -26 0 -23 0 -20 0 
-17 0 -14 0 +11 0 -8 0 +5 0 +3 0 *
So

0100000
+2 0 *

+1 0 ]]>
      </Part>
      <ElementMap/>
    </Property>
    <Property name="Suppress" type="App::PropertyBool" status="1">
      <Bool value="false"/>
    </Property>
    <Property name="SuppressedShape" type="Part::PropertyPartShape" status="1">
      <Part ElementMap="0.15.70200.4" brep="1">
<![CDATA[

CASCADE Topology V1, (c) Matra-Datavision
Locations 0
Curve2ds 0
Curves 0
Polygon3D 0
PolygonOnTriangulations 0
Surfaces 0
Triangulations 0

TShapes 0

*]]>
      </Part>
      <ElementMap/>
    </Property>
    <Property name="TaperAngle" type="App::PropertyAngle" status="1">
      <Float value="0"/>
    </Property>
    <Property name="TaperAngleRev" type="App::PropertyAngle" status="1">
      <Float value="0"/>
    </Property>
    <Property name="TaperInnerAngle" type="App::PropertyAngle" status="1">
      <Float value="0"/>
    </Property>
    <Property name="TaperInnerAngleRev" type="App::PropertyAngle" status="1">
      <Float value="-0"/>
    </Property>
    <Property name="TreeRank" type="App::PropertyInteger" status="2185">
      <Integer value="1"/>
    </Property>
    <Property name="Type" type="App::PropertyEnumeration" status="1">
      <Integer value="0"/>
    </Property>
    <Property name="UpToFace" type="App::PropertyLinkSub" status="1">
      <LinkSub value="" count="0">
      </LinkSub>
    </Property>
    <Property name="UsePipeForDraft" type="App::PropertyBool" status="1">
      <Bool value="false"/>
    </Property>
    <Property name="Visibility" type="App::PropertyBool" status="649">
      <Bool value="false"/>
    </Property>
    <Property name="_ProfileBasedVersion" type="App::PropertyInteger" status="67108865">
      <Integer value="0"/>
    </Property>
    <Property name="_Siblings" type="App::PropertyLinkList" status="218103809">
      <LinkList count="0">
      </LinkList>
    </Property>
    <Property name="_Version" type="App::PropertyInteger" status="67108865">
      <Integer value="0"/>
    </Property>
  </Properties>
</Object>
</Document>
