<?xml version='1.0' encoding='utf-8'?>
<!-- FreeCAD DocumentObject -->
<Document SchemaVersion="4" FileVersion="2">
<Object name="Solid029">
  <Properties Count="8" TransientCount="1">
    <_Property name="_ElementMapVersion" type="App::PropertyString" status="234881024"/>
    <Property name="ColoredElements" type="App::PropertyLinkSubHidden" status="218103808">
      <LinkSub value="" count="0">
      </LinkSub>
    </Property>
    <Property name="ExpressionEngine" type="App::PropertyExpressionEngine" status="67108864">
      <ExpressionEngine count="0"></ExpressionEngine>
    </Property>
    <Property name="Label" type="App::PropertyString" status="134217728">
      <String value="Latch_Shuttle:1"/>
    </Property>
    <Property name="Label2" type="App::PropertyString" status="128">
      <String value=""/>
    </Property>
    <Property name="Placement" type="App::PropertyPlacement" status="8388608">
      <PropertyPlacement Px="154.169259865133" Py="160.455099302405" Pz="207.580139896645" Q0="1" Q1="0" Q2="6e-16" Q3="-2.381258314217977e-15" A="3.141592653589798" Ox="1" Oy="0" Oz="6e-16"/>
    </Property>
    <Property name="Shape" type="Part::PropertyPartShape">
      <Part ElementMap="0.15.70200.4" brep="1">
<![CDATA[

CASCADE Topology V1, (c) Matra-Datavision
Locations 1
1
              1 8.74951153195801e-17 1.25019352509303e-15 154.169259865133 
8.74951153195748e-17              -1 4.24660306919122e-15 160.455099302405 
1.25019352509303e-15 -4.24660306919122e-15              -1 207.580139896645 
Curve2ds 124
1 9.4247779607693793 0 0 1 
1 3.1415926535897931 0 0 1 
1 0 5 1 0 
1 0 0 1 0 
1 3.1415926535897931 -5.7668381336568613e-16 -1 4.1710591317509788e-16 
1 1.5707963267948966 0.56568542494923824 0 -1 
1 -3.1415926535898042 0.56568542494924101 1 -5.8987683935823622e-16 
1 -3.1415926535898042 0.40000000000000036 1 0 
1 -0.12311781848623315 0.565685424949252 1.5700924586838792e-15 -1 
1 6.1600674886933513 0.56568542494924978 0 -1 
1 7.5223690760955559 -0.56568542494921414 3.925231146709671e-16 1 
1 12.566370614359178 8.3640342086139777e-16 -1 -1.035655768860994e-16 
1 4.4902950880164401 -0.56568542494920615 -1.2560739669470294e-14 1 
7 0 0  3 25 23  1.792890219163322 -4.1214927040449081e-15  1.7928902191633245 -0.0085709912871136402  1.7928902191633291 -0.025712973861332422  1.7928902191633371 -0.051425947722660147  1.7928902191633449 -0.07713892158399091  1.7928902191633587 -0.10285189544531717  1.792890219163354 -0.12856486930665084  1.7928902191633707 -0.15427784316797713  1.7928902191633822 -0.17999081702930794  1.7928902191633975 -0.20570379089063548  1.7928902191634148 -0.23141676475196402  1.7928902191634353 -0.25712973861329214  1.7928902191634593 -0.28284271247462017  1.7928902191634879 -0.30855568633595021  1.7928902191635208 -0.33426866019727836  1.7928902191635741 -0.35998163405860556  1.7928902191635938 -0.38569460791993837  1.7928902191636722 -0.4114075817812673  1.7928902191637737 -0.43712055564259539  1.7928902191638971 -0.46283352950392387  1.7928902191642093 -0.48854650336525102  1.7928902191643519 -0.51425947722658361  1.7928902191665019 -0.53997245108790315  1.7928902191667351 -0.55711443366214286  1.7928902191662019 -0.56568542494927487 
 0 4 0.025712973861328856 1 0.051425947722657711 1 0.077138921583986567 1 0.10285189544531542 1 0.12856486930664429 1 0.15427784316797313 1 0.17999081702930197 1 0.20570379089063084 1 0.23141676475195971 1 0.25712973861328858 1 0.2828427124746174 1 0.30855568633594627 1 0.33426866019727514 1 0.35998163405860395 1 0.38569460791993282 1 0.41140758178126169 1 0.43712055564259056 1 0.46283352950391943 1 0.48854650336524824 1 0.51425947722657717 1 0.53997245108790592 1 0.56568542494923479 4
1 0 -0.56568542494923579 1 -3.2954364771146502e-16 
1 12.28951738923557 0.40000000000000036 -1 0 
7 0 0  3 25 23  -0.65151342963418202 -0.56568542494923979  -0.65151342963414827 -0.55711443366213065  -0.65151342963416337 -0.5399724510879117  -0.65151342963429659 -0.51425947722658261  -0.65151342963420866 -0.4885465033652539  -0.65151342963427883 -0.46283352950392453  -0.65151342963423975 -0.43712055564259739  -0.65151342963422731 -0.41140758178127063  -0.65151342963425751 -0.38569460791994048  -0.65151342963423531 -0.35998163405861344  -0.65151342963424064 -0.33426866019728008  -0.65151342963422643 -0.30855568633595487  -0.65151342963424863 -0.28284271247462411  -0.6515134296342362 -0.25712973861329802  -0.65151342963422909 -0.23141676475196882  -0.65151342963424508 -0.20570379089063934  -0.65151342963423176 -0.17999081702931308  -0.65151342963424597 -0.15427784316798279  -0.65151342963423708 -0.12856486930665645  -0.65151342963423442 -0.10285189544532729  -0.6515134296342433 -0.077138921583997822  -0.6515134296342362 -0.051425947722671485  -0.65151342963424597 -0.025712973861341522  -0.65151342963424508 -0.0085709912871229955  -0.65151342963424064 -1.4444850619890727e-14 
 -0 4 0.025712973861328457 1 0.051425947722656913 1 0.077138921583985373 1 0.10285189544531383 1 0.12856486930664229 1 0.15427784316797075 1 0.1799908170292992 1 0.20570379089062765 1 0.23141676475195611 1 0.25712973861328459 1 0.28284271247461301 1 0.30855568633594149 1 0.33426866019726992 1 0.3599816340585984 1 0.38569460791992682 1 0.4114075817812553 1 0.43712055564258379 1 0.46283352950391221 1 0.48854650336524069 1 0.51425947722656917 1 0.5399724510878976 1 0.56568542494922602 4
1 5.631671877545342 1.0048591735576156e-14 0 1 
1 -0.65151342963418202 -0.56568542494923979 1 -1.4352395356377539e-14 
1 -3.1415926535897847 -1.6713343365743576e-15 1 4.9779898507292882e-16 
1 -3.1415926535897847 0.40000000000000036 1 0 
1 6.2831853071795862 -3.0481858021499007e-15 -1 6.635043155603099e-16 
1 1.5707963267948966 0.56568542494923379 0 -1 
1 -6.2831853071795862 0.56568542494923379 1 0 
1 7.0257543750827827 9.6000000000000068 -1 0 
1 -0.085658190988503691 0.56568542494923135 -1.5700924586839e-15 -1 
1 6.3688434981680899 -2.5121479338940493e-15 0 1 
1 9.4247779607693793 0.5656854249492328 -1 0 
1 5.5972887922244272 -2.5121479338940493e-15 0 1 
1 6.969081822134747 0.56568542494926266 5.4953236053930638e-15 -1 
1 3.1415926535897931 7.9956378120944859e-15 1 -3.2559556886138429e-15 
1 3.1415926535897931 9.6000000000000068 1 0 
1 12.566370614359176 -7.5070788626883416e-15 -1 1.2570462926367897e-15 
1 8.8817841970012523e-16 0.56568542494923235 1 2.3187807594493544e-16 
1 12.534073082657986 9.6000000000000068 -1 0 
1 5.5326937288221174 0.56568542494920337 1.083363796491875e-13 -1 
1 1.5707963267948966 0 0 -1 
1 3.1415926535897931 9.6000000000000068 -1 0 
1 -2.4177533994354601 0.56568542494923291 1 1.3108374207960825e-16 
1 -0.12311781848623315 0 0 1 
1 6.1600674886933513 0 0 1 
1 6.3688434981680899 0 0 -1 
1 0.82822725889170001 0 0 -1 
1 5.5972887922244272 0 0 1 
1 5.5649912605232377 0 0 1 
1 9.4247779607693793 0.40000000000000036 -1 0 
1 -3.4417118155731199 -0.56568542494922769 1 -3.1656739766599129e-15 
1 1.792890219163322 0 0 1 
1 7.7992223012191317 0 0 1 
1 3.1415926535897896 9.6000000000000068 -1 0 
1 3.7122810483542832 4.0742992280222771e-16 1 -2.7298654020128516e-16 
1 -0.65151342963411274 0 0 1 
1 5.6316718775453438 0 0 1 
1 9.4247779607693793 9.6000000000000068 -1 0 
1 -4.4408920985006262e-16 3.1195009623490717e-14 1 -8.7857290669200553e-15 
1 5.8741324325632034 0 0 -1 
1 5.874132432563143 0 0 -1 
1 3.1415926535897927 0.40000000000000036 1 0 
1 3.1415926535897927 0.56568542494921403 1 8.5421168262194407e-15 
1 5.0440015382636236 0 0 1 
1 4.7671483131400096 0 0 1 
1 -0.27685322512360777 9.6000000000000068 1 0 
1 -0.27685322512360777 -3.7080516953921219e-15 1 8.2852461508881564e-16 
1 9.4247779607693793 9.6000000000000068 -1 0 
1 -4.4408920985006262e-16 0 1 0 
1 5.4979754817283446 0 0 -1 
1 5.4979754817283712 0 0 -1 
1 3.1415926535897927 0.40000000000000036 1 0 
1 3.1415926535897927 0.56568542494928231 1 -1.9099340270421756e-14 
1 3.8920842319472668 0 0 1 
1 7.0013793538358691 0 0 -1 
1 -0.82822725889169835 0 0 1 
1 2.8414734916064681 -2.1015571491976951e-14 -1 6.5119113772276441e-15 
1 7.0257543750827818 1.1774490437565196e-14 -1 -1.4691881273121044e-15 
1 9.4247779607693793 -2.8682861689596644e-14 -1 8.7857290669200522e-15 
1 9.4247779607693793 3.9858458576989533e-15 -1 -9.4568969150853284e-16 
1 9.4247779607693793 0 -1 0 
1 9.4247779607693793 -8.5592750791865785e-15 -1 1.759874104810118e-15 
1 6.2508877754783843 3.561747501029329e-15 -1 -6.0119605300020073e-16 
1 6.2831853071795889 -2.2145111871998861e-15 -1 1.040258660659391e-15 
1 6.2831853071795862 -0.5656854249492328 -1 0 
1 3.8654319077441297 3.9582820706256477e-15 -1 -9.7324713074190249e-16 
1 6.2831853071795862 2.4616519637913922e-15 -1 -1.7109887130098541e-15 
1 6.2831853071795791 -0.5656854249492328 -1 0 
1 12.289517389235566 0.56568542494923912 -1 -7.3231921713657541e-16 
1 -5.540616239276388 0.40000000000000036 1 0 
1 -5.540616239276388 0.56568542494923535 1 6.0321651541615026e-16 
1 -0.032297531701187765 0.40000000000000036 1 0 
1 -6.3154828388807847 0.56568542494923635 1 4.6375615188987158e-16 
1 9.4247779607693793 9.6000000000000068 -1 0 
1 -4.4408920985006262e-16 0.56568542494922924 1 7.6047822494464485e-16 
1 3.1415926535897953 0.40000000000000036 1 0 
1 3.1415926535897953 0.56568542494923857 1 -6.9134384085876799e-16 
1 9.4247779607693793 9.6000000000000068 -1 0 
1 0 0.56568542494923701 1 -5.3496287501116879e-16 
1 3.141592653589798 0.40000000000000036 1 0 
1 3.141592653589798 0.56568542494923812 1 5.3496287501116879e-16 
1 5.5326937288221361 5.2755106611775407e-14 -8.1644807851554791e-14 1 
1 3.9268024790411031 -5.1813051136565137e-15 -5.3383143595252084e-14 1 
1 3.9268024790410365 -0.56568542494918006 0 1 
1 3.7931060832240369 -0.56568542494922269 -7.8504622934191004e-16 1 
7 0 0  3 25 23  7.505387131578245 -0.56568542494923491  7.5053871315782175 -0.55711443366212621  7.5053871315782308 -0.53997245108790803  7.5053871315783374 -0.51425947722657839  7.5053871315783667 -0.48854650336525013  7.5053871315783027 -0.46283352950392032  7.5053871315783312 -0.43712055564258911  7.5053871315782734 -0.41140758178126757  7.5053871315783365 -0.38569460791993748  7.5053871315783143 -0.35998163405860872  7.5053871315783329 -0.33426866019727852  7.5053871315783347 -0.30855568633595409  7.5053871315783152 -0.28284271247462289  7.5053871315783294 -0.25712973861329347  7.5053871315782867 -0.23141676475196654  7.5053871315783232 -0.20570379089063687  7.5053871315783045 -0.17999081702931166  7.5053871315783178 -0.15427784316798066  7.5053871315783169 -0.12856486930665625  7.5053871315783134 -0.10285189544532569  7.5053871315783285 -0.077138921583996892  7.5053871315783001 -0.051425947722669507  7.5053871315783205 -0.025712973861340575  7.5053871315783205 -0.0085709912871224196  7.5053871315783134 -1.3895318259351424e-14 
 0 4 0.025712973861328255 1 0.051425947722656511 1 0.077138921583984763 1 0.10285189544531302 1 0.12856486930664127 1 0.15427784316796953 1 0.17999081702929778 1 0.20570379089062604 1 0.2314167647519543 1 0.25712973861328253 1 0.28284271247461079 1 0.30855568633593905 1 0.33426866019726731 1 0.35998163405859557 1 0.38569460791992383 1 0.41140758178125209 1 0.43712055564258034 1 0.4628335295039086 1 0.48854650336523686 1 0.51425947722656506 1 0.53997245108789338 1 0.56568542494922158 4
1 5.060983482780836 -0.56568542494923491 1 0 
7 0 0  3 25 23  5.060983482780836 -0.56568542494923491  5.060983482780812 -0.5571144336621271  5.0609834827808191 -0.53997245108790837  5.0609834827809275 -0.51425947722657694  5.0609834827808369 -0.48854650336525146  5.0609834827809683 -0.46283352950392453  5.0609834827808937 -0.43712055564259034  5.0609834827808893 -0.41140758178126285  5.060983482780852 -0.38569460791993265  5.0609834827809008 -0.35998163405860661  5.06098348278086 -0.33426866019727641  5.0609834827808946 -0.3085556863359491  5.0609834827808875 -0.28284271247462306  5.0609834827809026 -0.2571297386132918  5.0609834827808777 -0.23141676475196377  5.0609834827809053 -0.20570379089063259  5.0609834827808822 -0.17999081702930339  5.0609834827809035 -0.15427784316797724  5.0609834827808875 -0.12856486930664623  5.0609834827808839 -0.10285189544532214  5.0609834827808999 -0.077138921583989745  5.0609834827808839 -0.051425947722661174  5.0609834827808955 -0.025712973861333577  5.0609834827808964 -0.0085709912871159196  5.0609834827808919 -7.14392068701119e-15 
 0 4 0.025712973861328651 1 0.051425947722657302 1 0.077138921583985956 1 0.1028518954453146 1 0.12856486930664326 1 0.15427784316797191 1 0.17999081702930056 1 0.20570379089062921 1 0.23141676475195785 1 0.25712973861328653 1 0.28284271247461518 1 0.30855568633594382 1 0.33426866019727247 1 0.35998163405860112 1 0.38569460791992977 1 0.41140758178125841 1 0.43712055564258706 1 0.46283352950391571 1 0.48854650336524436 1 0.51425947722657306 1 0.53997245108790171 1 0.56568542494923035 4
1 7.7992223012191593 0.56568542494926111 0 -1 
1 -0.84695707264056352 0.56568542494923313 -1.5700924586837871e-15 -1 
1 4.7671483131399874 0.56568542494922314 -1.0990647210787142e-14 -1 
1 0.84695707264056797 0.56568542494924756 1.5700924586838909e-15 -1 
1 3.2647104720760276 1.5072887603364372e-14 0 -1 
1 4.3807764225057646 7.7719576704847304e-15 -1.5700924586836266e-15 1 
1 3.550645528206176 1.5072887603364372e-14 0 -1 
1 3.5506455282062364 0.56568542494927887 7.3009299328798263e-14 -1 
1 5.4979754817283428 5.5267254545668861e-14 0 1 
1 5.4979754817282762 -5.1028004907222723e-15 4.3962588843148411e-14 1 
1 5.0440015382636236 0.56568542494930396 6.2803698347344646e-15 -1 
1 3.8920842319472437 5.2755106611774877e-14 7.6149484246160865e-14 1 
1 5.874132432563143 0.56568542494928331 -7.3794345558139513e-14 -1 
1 5.8741324325632034 0.56568542494925489 0 -1 
1 0.71819404665636211 2.3551386880256619e-16 5.8878467200644712e-16 1 
1 -0.71819404665632991 8.321490031024004e-15 -2.3551386880255724e-14 1 
1 0.38577735297183263 2.0097183471152313e-14 3.9252311467092776e-16 -1 
1 -0.38577735297183136 -4.7730810743986743e-14 0 -1 
1 0.82822725889168869 4.0037357696436247e-14 6.6728929494065428e-15 1 
1 -0.82822725889169835 0.56568542494923824 -1.5700924586837751e-15 -1 
Curves 92
1 -7.5 5 -22.590120321532901 1 0 1.0204255741040001e-16 
2 -2.5 5 -24.940120321532898 1 0 1.0204255741040001e-16 1.0204255741040001e-16 0 -1 -0 1 0 2.3500000000000001
2 -7.5 5 -24.940120321532898 1 0 1.0204255741040001e-16 1.0204255741040001e-16 0 -1 -0 1 0 2.3500000000000001
2 -3.5 10 -28.284271247461898 0 1 0 0 -0 1 1 0 -0 0.59999999999999998
1 -2.5 9.5999999999999996 -28.284271247461898 -0.70710678118654802 0.70710678118654702 0 
2 -3.5 9.5999999999999996 -28.284271247461898 0 -1 0 1.0842021724855e-14 0 1 -1 0 1.0842021724855e-14 1
1 -3.62280701754386 9.5999999999999996 -29.2767018175483 0.086837674882558169 0.70710678118654591 0.70175438596491391 
1 -13.7980665639212 9.5999999999999996 -22.068736796203599 0.66858259654412322 0.70710678118654613 0.23021144975504604 
2 -15.5 10 -22.654759474226498 0 -1 0 4.7310640253912901e-15 0 1 -1 0 4.7310640253912901e-15 2.2000000000000002
1 -17.255789049742098 9.5999999999999996 -23.051250095560601 -0.68973907966982384 0.70710678118654602 -0.15575622612347398 
2 -15.5 9.5999999999999996 -22.654759474226498 0 1 0 0 -0 1 1 0 -0 1.8
1 -17.645964394129201 10 -23.1393591225238 -0.42878285510876002 -0.70710678118655512 -0.56226796384354816 
2 -17.645964394129201 9.5999999999999996 -23.1393591225238 0 -1 0 -8.6736173798840102e-15 0 1 -1 -0 -8.6736173798840102e-15 0.40000000000000102
2 -3.5 0 -21.595969395603898 0 -1 0 0 0 1 -1 0 0 0.59999999999999998
1 -2.5 0.39999999999999403 -21.595969395603898 -0.70710678118655312 -0.70710678118654202 0 
2 -3.5 0.39999999999999403 -21.595969395603898 0 1 0 0 -0 1 1 0 -0 1
1 -3.58555347907037 0.39999999999999403 -20.599635815812999 0.060495445204760016 -0.70710678118654624 -0.70451423059401708 
2 -5.1255161023370297 0 -2.6656313795767499 0 1 0 0 -0 1 1 0 -0 18.399999999999999
1 -16.526122740053101 0.39999999999999403 -16.594959012024201 -0.44785812573163603 -0.70710678118654291 -0.54719566812626796 
2 -5.1255161023370297 0.39999999999999403 -2.6656313795767499 0 -1 0 0 0 1 -1 0 0 18
2 -17.159489775481799 0 -17.368810547160201 0 -1 0 0 0 1 -1 0 0 0.59999999999999998
2 -17.159489775481799 0.39999999999999403 -17.368810547160201 0 1 0 0 -0 1 1 0 -0 1
1 -17.8414881355442 0.39999999999999403 -16.637456845540999 0.48224566515829898 -0.70710678118654602 -0.51714516186079895 
1 -2.5 10 -28.284271247461898 0 1 0 
2 -3.5 0.39999999999999403 -28.284271247461898 0 1 0 0 -0 1 1 0 -0 1
1 -3.62280701754386 10 -29.2767018175483 0 -1 0 
1 -3.58555347907037 10 -20.599635815812999 0 1 0 
1 -16.526122740053101 10 -16.594959012024201 0 -1 0 
2 -5.1255161023370297 9.5999999999999996 -2.6656313795767499 0 1 0 0 -0 1 1 0 -0 18
1 -17.255789049742098 10 -23.051250095560601 0 -1 0 
2 -17.645964394129201 0.39999999999999403 -23.1393591225238 0 1 0 0 -0 1 1 0 -0 0.40000000000000102
1 -17.8885206057323 10 -23.457425914586 0 -1 0 
2 0 0.39999999999999403 0 0 1 0 0 -0 1 1 0 -0 29.5
1 -11.7333453670698 10 -27.0661893604745 0 1 0 
2 0 9.5999999999999996 0 0 -1 0 0 0 1 -1 0 0 29.5
1 -12.2811234217515 10 -26.474259570508799 0 -1 0 
1 -13.7980665639212 0.39999999999999403 -22.068736796203599 -0.32556815445715692 0 0.94551857559931674 
1 -13.7980665639212 10 -22.068736796203599 0 -1 0 
1 -12.2811234217515 9.5999999999999996 -26.474259570508799 0.32556815445715692 0 -0.94551857559931674 
2 -15.5 0.39999999999999403 -22.654759474226498 0 -1 0 1.9274705288631201e-15 0 1 -1 0 1.9274705288631201e-15 1.8
2 0 0.39999999999999403 0 0 1 0 0 -0 1 1 0 -0 29.5
1 -20.855721011420101 10 -20.8635783386698 0 1 0 
2 0 9.5999999999999996 0 0 -1 0 0 0 1 -1 0 0 29.5
1 -20.830745777875201 10 -19.424984693366799 0 -1 0 
1 -21.5749341977656 0.39999999999999403 -20.1189516218436 0.7313537016191729 0 0.68199836006249592 
1 -17.8414881355442 10 -16.637456845540999 0 1 0 
1 -20.830745777875201 9.5999999999999996 -19.424984693366799 -0.7313537016191729 0 -0.68199836006249592 
1 -2.5 10 -21.595969395603898 0 -1 0 
1 -2.5 0.39999999999999403 -29.154759474226498 0 0 -1 
1 -2.5 9.5999999999999996 -21.595969395603898 0 0 1 
2 -5.1255161023370297 10 -2.6656313795767499 0 -1 0 1.7912905458456201e-15 0 1 -1 0 1.7912905458456201e-15 18.399999999999999
2 -3.5 10 -21.595969395603898 0 1 0 0 -0 1 1 0 -0 0.59999999999999998
1 -2.8999999999999999 10 -28.284271247461898 0 0 -1 
2 0 10 0 0 1 0 0 -0 1 1 0 -0 29.100000000000001
2 -11.3356048461521 10 -26.148691416051602 0 1 0 0 -0 1 1 0 -0 0.59999999999999998
1 -13.4198591336815 10 -21.938509534420799 -0.32556815445715692 0 0.94551857559931674 
2 0 10 0 0 1 0 0 -0 1 1 0 -0 29.100000000000001
2 -20.1487474178127 10 -20.156338394986101 0 1 0 0 -0 1 1 0 -0 0.59999999999999998
1 -17.5686887915193 10 -16.929998326188699 0.7313537016191729 0 0.68199836006249592 
2 -17.159489775481799 10 -17.368810547160201 0 1 0 0 -0 1 1 0 -0 0.59999999999999998
1 -18.750773794658699 0 -6.45640918804924 0.32556815445715692 0 -0.94551857559931674 
2 -11.3356048461521 0 -26.148691416051602 0 -1 0 2.8912057932946798e-15 0 1 -1 0 2.8912057932946798e-15 0.59999999999999998
2 0 0 0 0 -1 0 0 0 1 -1 0 0 29.100000000000001
2 -3.5 0 -28.284271247461898 0 -1 0 2.8912057932946798e-15 0 1 -1 0 2.8912057932946798e-15 0.59999999999999998
1 -2.8999999999999999 0 0 0 0 1 
1 0.27279934402500999 0 -0.29254148064768098 -0.7313537016191729 0 -0.68199836006249592 
2 -20.1487474178127 0 -20.156338394986101 0 -1 0 0 0 1 -1 0 0 0.59999999999999998
2 0 0 0 0 -1 0 -7.1054273576010003e-15 0 1 -1 -0 -7.1054273576010003e-15 29.100000000000001
2 -15.5 0 -22.654759474226498 0 1 0 0 -0 1 1 0 -0 2.2000000000000002
2 -3.5 9.5999999999999996 -21.595969395603898 0 -1 0 0 0 1 -1 0 0 1
2 -17.159489775481799 9.5999999999999996 -17.368810547160201 0 -1 0 0 0 1 -1 0 0 1
2 -20.1487474178127 0.39999999999999403 -20.156338394986101 0 1 0 0 -0 1 1 0 -0 1
2 -20.1487474178127 9.5999999999999996 -20.156338394986101 0 -1 0 -3.4694469519536099e-15 0 1 -1 -0 -3.4694469519536099e-15 1
2 -11.3356048461521 0.39999999999999403 -26.148691416051602 0 1 0 0 -0 1 1 0 -0 1
2 -11.3356048461521 9.5999999999999996 -26.148691416051602 0 -1 0 -3.4694469519536099e-15 0 1 -1 -0 -3.4694469519536099e-15 1
1 -20.557946433850201 0 -19.717526174014498 -0.48224566515830269 0.70710678118654158 0.51714516186080162 
1 -20.572931573977201 0 -20.580682361196299 -0.49990582215965995 0.70710678118654191 -0.50009416010475705 
1 -17.645964394129201 0 -23.1393591225238 -0.42878285510876274 0.70710678118654258 -0.5622679638435617 
1 -17.645964394129201 0 -23.1393591225238 0.68973907966982995 0.70710678118654002 0.15575622612347401 
1 -2.5 0.39999999999999403 -28.284271247461898 -0.70710678118655312 -0.70710678118654202 0 
1 -13.4198591336815 0 -21.938509534420799 -0.66858259654412611 0.70710678118654313 -0.23021144975504709 
1 -3.62280701754386 0.39999999999999403 -29.2767018175483 0.086837674882559668 -0.7071067811865398 0.7017543859649199 
1 -11.9029159915117 0 -26.3440323087259 -0.66858259654412455 0.70710678118654458 -0.2302114497550472 
1 -11.7333453670698 0.39999999999999403 -27.0661893604745 0.28124501949352088 -0.70710678118654158 0.64876901822613064 
1 -20.572931573977201 10 -20.580682361196299 -0.49990582215965884 -0.70710678118654791 -0.50009416010474994 
1 -12.2811234217515 9.5999999999999996 -26.474259570508799 0.66858259654411689 0.7071067811865519 0.23021144975504698 
1 -20.557946433850201 10 -19.717526174014498 -0.48224566515829503 -0.70710678118654713 0.51714516186080106 
1 -11.7333453670698 9.5999999999999996 -27.0661893604745 0.28124501949351793 0.70710678118654791 0.64876901822612498 
1 -17.5686887915193 10 -16.929998326188699 -0.48224566515829886 -0.70710678118654691 0.51714516186079784 
1 -16.779469554224601 10 -16.9044996260786 0.44785812573163386 -0.70710678118654591 0.54719566812626586 
1 -3.5513320874422201 10 -20.998169247729301 -0.060495445204758171 -0.70710678118654979 0.70451423059401364 
1 -2.5 9.5999999999999996 -21.595969395603898 -0.70710678118654757 0.70710678118654757 0 
Polygon3D 0
PolygonOnTriangulations 0
Surfaces 43
2 -7.5 5 -24.940120321532898 1 0 1.0204255741040001e-16 1.0204255741040001e-16 0 -1 -0 1 0 2.3500000000000001
1 -2.5 10 -29.154759474226498 -1 0 0 0 0 1 0 1 -0 
1 -7.5 5 -24.940120321532898 1 0 1.0204255741040001e-16 1.0204255741040001e-16 0 -1 -0 1 0 
3 -3.5 10 -28.284271247461898 0 -1 0 0 0 -1 1 0 0 0.59999999999999998
0.78539816339744795
1 0 10 0 0 1 0 0 -0 1 1 0 -0 
1 -2.8999999999999999 10 0 0.70710678118654757 0.70710678118654757 0 0 -0 1 0.70710678118654757 -0.70710678118654757 -0 
2 -3.5 10 -28.284271247461898 0 -1 0 0 0 -1 1 0 0 1
3 0 10 0 0 -1 0 0 0 -1 1 0 0 29.100000000000001
0.78539816339745205
3 -15.5 10 -22.654759474226498 0 1 0 0 -0 1 1 0 -0 2.2000000000000002
0.78539816339745006
1 -18.750773794658699 10 -6.45640918804924 -0.66858259654412477 0.7071067811865448 -0.2302114497550459 0.32556815445715703 5.5511151231257827e-17 -0.94551857559931674 -0.66858259654411956 -0.70710678118655035 -0.23021144975504418 
3 -17.645964394129201 9.5999999999999996 -23.1393591225238 0 -1 0 0 0 -1 1 0 0 0.40000000000000102
0.78539816339744795
2 -15.5 10 -22.654759474226498 0 -1 0 -0.27333006018485395 0 0.96192030761354874 -0.96192030761354874 -0 -0.27333006018485395 1.8
3 0 10 0 0 -1 0 0 0 -1 1 0 0 29.100000000000001
0.78539816339744795
2 -17.645964394129201 10 -23.1393591225238 0 -1 0 0 0 -1 1 0 0 0.40000000000000102
3 -3.5 0 -21.595969395603898 0 1 0 0 -0 1 1 0 -0 0.59999999999999998
0.78539816339745605
1 0 0 0 0 1 0 0 -0 1 1 0 -0 
1 -2.5 0.39999999999999403 -29.154759474226498 -0.70710678118654202 0.70710678118655301 0 0 0 -1 -0.70710678118655301 -0.70710678118654202 -0 
2 -3.5 10 -21.595969395603898 0 -1 0 0.67618286022703611 0 0.73673383221838307 -0.73673383221838307 0 0.67618286022703611 1
3 -5.1255161023370297 0.39999999999999403 -2.6656313795767499 0 -1 0 0 0 -1 1 0 0 18
0.78539816339745205
3 -17.159489775481799 0 -17.368810547160201 0 1 0 0 -0 1 1 0 -0 0.59999999999999998
0.78539816339745505
2 -5.1255161023370297 10 -2.6656313795767499 0 -1 0 0 0 -1 1 0 0 18
2 -17.159489775481799 10 -17.368810547160201 0 -1 0 -0.032291916903688191 0 0.99947848005981876 -0.99947848005981876 -0 -0.032291916903688191 1
1 -21.5749341977656 0.39999999999999403 -20.1189516218436 0.48224566515829298 0.70710678118655101 -0.51714516186079795 0.73135370161917324 3.05311331771918e-16 0.68199836006249581 0.48224566515829792 -0.70710678118654424 -0.51714516186080262 
3 -3.5 0 -28.284271247461898 0 1 0 0.66226617853252312 0 -0.74926864926535408 -0.74926864926535408 0 -0.66226617853252312 0.59999999999999998
0.78539816339745605
2 0 10 0 0 -1 0 0 0 -1 1 0 0 29.5
3 -5.1255161023370297 10 -2.6656313795767499 0 1 0 -0.29563404435372792 0 -0.95530126756906275 -0.95530126756906275 0 0.29563404435372792 18.399999999999999
0.78539816339744795
3 -17.645964394129201 0.39999999999999403 -23.1393591225238 0 1 0 0.54021148104932115 0 -0.84152929583140423 -0.84152929583140423 0 -0.54021148104932115 0.40000000000000102
0.78539816339745605
2 0 10 0 0 -1 0 0 0 -1 1 0 0 29.5
3 0 0.39999999999999403 0 0 1 0 0 -0 1 1 0 -0 29.5
0.78539816339745705
2 -11.3356048461521 10 -26.148691416051602 0 -1 0 0 0 -1 1 0 0 1
1 -13.7980665639212 10 -22.068736796203599 0.94551857559931674 0 0.32556815445715692 0.32556815445715692 0 -0.94551857559931674 -0 1 0 
1 -13.7980665639212 0.39999999999999403 -22.068736796203599 0.668582596544119 0.70710678118655101 0.23021144975504401 -0.32556815445715703 -8.3266726846886728e-17 0.94551857559931674 0.66858259654412533 -0.70710678118654413 0.23021144975504607 
3 -15.5 0.39999999999999403 -22.654759474226498 0 -1 0 -0.27333006018485489 0 0.96192030761354852 -0.96192030761354852 -0 -0.27333006018485489 1.8
0.78539816339745605
3 0 0.39999999999999403 0 0 1 0 0 -0 1 1 0 -0 29.5
0.78539816339745205
2 -20.1487474178127 10 -20.156338394986101 0 -1 0 0 0 -1 1 0 0 1
1 -21.5749341977656 10 -20.1189516218436 0.68199836006249592 0 -0.7313537016191729 -0.7313537016191729 0 -0.68199836006249592 0 1 0 
1 0.27279934402501099 10 -0.29254148064768198 -0.48224566515829576 0.70710678118654768 0.51714516186079973 -0.73135370161917279 -2.7755575615628914e-16 -0.68199836006249615 -0.48224566515829564 -0.70710678118654746 0.51714516186080017 
3 -3.5 10 -21.595969395603898 0 -1 0 0.67618286022703611 0 0.73673383221838307 -0.73673383221838307 0 0.67618286022703611 0.59999999999999998
0.78539816339744795
3 -11.3356048461521 10 -26.148691416051602 0 -1 0 0 0 -1 1 0 0 0.59999999999999998
0.78539816339745006
3 -20.1487474178127 10 -20.156338394986101 0 -1 0 0 0 -1 1 0 0 0.59999999999999998
0.78539816339744895
3 -17.159489775481799 10 -17.368810547160201 0 -1 0 -0.032291916903698911 0 0.99947848005981832 -0.99947848005981832 -0 -0.032291916903698911 0.59999999999999998
0.78539816339744795
3 -11.3356048461521 0 -26.148691416051602 0 1 0 0 -0 1 1 0 -0 0.59999999999999998
0.78539816339745405
3 -20.1487474178127 0 -20.156338394986101 0 1 0 0 -0 1 1 0 -0 0.59999999999999998
0.78539816339745905
Triangulations 0

TShapes 235
Ve
1e-07
-7.5 5 -22.5901203215329
0 0

0101101
*
Ve
1e-07
-2.5 5 -22.5901203215329
0 0

0101101
*
Ed
 1e-07 1 1 0
1  1 0 0 5
3  1 2CN 1 0 0 5
0

0101000
+235 0 -234 0 *
Ed
 1e-07 1 1 0
1  2 0 3.14159265358979 9.42477796076938
2  3 1 0 3.14159265358979 9.42477796076938
4 C0 1 0 2 0
0

0101000
+234 0 -234 0 *
Ed
 1e-07 1 1 0
1  3 0 3.14159265358979 9.42477796076938
2  4 1 0 3.14159265358979 9.42477796076938
4 C0 1 0 3 0
0

0101000
+235 0 -235 0 *
Wi

0101100
+233 0 -232 0 -233 0 +231 0 *
Fa
0  1e-07 1 0

0101000
+230 0 *
Ve
1e-07
-2.9 10 -28.2842712474619
0 0

0101101
*
Ve
1e-07
-3.57368421052632 10 -28.8797295895138
0 0

0101101
*
Ed
 1e-07 1 1 0
1  4 0 1.5707963267949 3.26471047207602
2  5 4 0 1.5707963267949 3.26471047207602
4 C0 4 0 5 0
0

0101000
+228 0 -227 0 *
Ve
1e-07
-2.5 9.6 -28.2842712474619
0 0

0101101
*
Ed
 1e-07 1 1 0
1  5 0 0 0.565685424949238
2  6 4 0 0 0.565685424949238
4 G1 4 0 6 0
0

0101000
+225 0 -228 0 *
Ve
1e-07
-3.62280701754386 9.6 -29.2767018175483
0 0

0101101
*
Ed
 1e-07 1 1 0
1  6 0 3.01847483510357 4.7123889803847
2  7 4 0 3.01847483510357 4.7123889803847
2  8 7 0 3.01847483510357 4.7123889803847
4 C0 4 0 7 0
0

0101000
+223 0 -225 0 *
Ed
 1e-07 1 1 0
1  7 0 0 0.5656854249492
2  9 4 0 0 0.5656854249492
2  10 8 0 0 0.5656854249492
4 G1 4 0 8 0
0

0101000
+223 0 -227 0 *
Wi

0101100
-226 0 -224 0 -222 0 +221 0 *
Fa
0  1e-07 4 0

0101000
+220 0 *
Ve
1e-07
-13.7980665639212 9.6 -22.0687367962036
0 0

0101101
*
Ve
1e-07
-13.4198591336815 10 -21.9385095344208
0 0

0101101
*
Ed
 1e-07 1 1 0
1  8 0 0 0.565685424949206
2  11 9 0 0 0.565685424949206
4 G1 9 0 10 0
0

0101000
+218 0 -217 0 *
Ve
1e-07
-17.6459643941292 10 -23.1393591225238
0 0

0101101
*
Ed
 1e-07 1 1 0
1  9 0 5.0440015382636 8.07607552634277
2  12 9 0 5.0440015382636 8.07607552634277
4 C0 9 0 5 0
0

0101000
+217 0 -215 0 *
Ve
1e-07
-17.2557890497421 9.6 -23.0512500955606
0 0

0101101
*
Ed
 1e-07 1 1 0
1  10 0 0 0.565685424949235
2  13 9 0 0 0.565685424949235
2  14 11 0 0 0.565685424949235
4 G1 9 0 11 0
0

0101000
+213 0 -215 0 *
Ed
 1e-07 1 1 0
1  11 0 4.49029508801644 7.52236907609556
2  15 9 0 4.49029508801644 7.52236907609556
2  16 12 0 4.49029508801644 7.52236907609556
4 C0 9 0 12 0
0

0101000
+213 0 -218 0 *
Wi

0101100
+216 0 +214 0 -212 0 +211 0 *
Fa
0  1e-07 9 0

0101000
+210 0 *
Ve
1e-07
-17.8885206057323 9.6 -23.457425914586
0 0

0101101
*
Ed
 1e-07 1 1 0
1  12 0 -0 0.565685424949226
2  17 11 0 -0 0.565685424949226
2  18 13 0 -0 0.565685424949226
4 G1 11 0 13 0
0

0101000
+215 0 -208 0 *
Ed
 1e-07 1 1 1
2  19 11 0 0 2.44440364880038
0

0101000
+215 0 -215 0 *
Ed
 1e-07 1 1 0
1  13 0 2.49007922395567 4.93448287275311
2  20 11 0 2.49007922395567 4.93448287275311
2  21 14 0 2.49007922395567 4.93448287275311
4 C0 11 0 14 0
0

0101000
+208 0 -213 0 *
Wi

0101100
-207 0 +206 0 -212 0 -205 0 *
Fa
0  1e-07 11 0

0101000
+204 0 *
Ve
1e-07
-2.9 0 -21.5959693956039
0 0

0101101
*
Ve
1e-07
-3.55133208744222 0 -20.9981692477293
0 0

0101101
*
Ed
 1e-07 1 1 0
1  14 0 4.71238898038469 6.36884349816808
2  22 15 0 4.71238898038469 6.36884349816808
4 C0 15 0 16 0
0

0101000
+202 0 -201 0 *
Ve
1e-07
-2.5 0.399999999999994 -21.5959693956039
0 0

0101101
*
Ed
 1e-07 1 1 0
1  15 0 0 0.565685424949234
2  23 15 0 0 0.565685424949234
4 G1 15 0 17 0
0

0101000
+199 0 -202 0 *
Ve
1e-07
-3.58555347907037 0.399999999999994 -20.599635815813
0 0

0101101
*
Ed
 1e-07 1 1 0
1  16 0 6.19752711619108 7.85398163397448
2  24 15 0 6.19752711619108 7.85398163397448
2  25 18 0 6.19752711619108 7.85398163397448
4 C0 15 0 18 0
0

0101000
+197 0 -199 0 *
Ed
 1e-07 1 1 0
1  17 0 0 0.565685424949192
2  26 15 0 0 0.565685424949192
2  27 19 0 0 0.565685424949192
4 G1 15 0 19 0
0

0101000
+197 0 -201 0 *
Wi

0101100
-200 0 -198 0 -196 0 +195 0 *
Fa
0  1e-07 15 0

0101000
+194 0 *
Ve
1e-07
-16.7794695542246 0 -16.9044996260786
0 0

0101101
*
Ed
 1e-07 1 1 0
1  18 0 3.05593446260129 3.82748916854495
2  28 19 0 3.05593446260129 3.82748916854495
4 C0 19 0 16 0
0

0101000
+201 0 -192 0 *
Ve
1e-07
-16.5261227400531 0.399999999999994 -16.5949590120242
0 0

0101101
*
Ed
 1e-07 1 1 0
1  19 0 -0 0.565685424949254
2  29 19 0 -0 0.565685424949254
2  30 20 0 -0 0.565685424949254
4 G1 19 0 20 0
0

0101000
+190 0 -192 0 *
Ed
 1e-07 1 1 0
1  20 0 2.45569613863463 3.2272508445783
2  31 19 0 2.45569613863463 3.2272508445783
2  32 21 0 2.45569613863463 3.2272508445783
4 C0 19 0 21 0
0

0101000
+190 0 -197 0 *
Wi

0101100
+195 0 +191 0 -189 0 +188 0 *
Fa
0  1e-07 19 0

0101000
+187 0 *
Ve
1e-07
-17.5686887915193 0 -16.9299983261887
0 0

0101101
*
Ed
 1e-07 1 1 0
1  21 0 5.59728879222445 7.03367688553715
2  33 20 0 5.59728879222445 7.03367688553715
4 C0 20 0 16 0
0

0101000
+192 0 -185 0 *
Ve
1e-07
-17.8414881355442 0.399999999999994 -16.637456845541
0 0

0101101
*
Ed
 1e-07 1 1 0
1  22 0 5.53269372882212 6.96908182213475
2  34 20 0 5.53269372882212 6.96908182213475
2  35 22 0 5.53269372882212 6.96908182213475
4 C0 20 0 22 0
0

0101000
+183 0 -190 0 *
Ed
 1e-07 1 1 0
1  23 0 0 0.565685424949202
2  36 20 0 0 0.565685424949202
4 G1 20 0 23 0
0

0101000
+183 0 -185 0 *
Wi

0101100
-184 0 -189 0 -182 0 +181 0 *
Fa
0  1e-07 20 0

0101000
+180 0 *
Ve
1e-07
-2.5 0.399999999999994 -28.2842712474619
0 0

0101101
*
Ed
 1e-07 1 1 0
1  24 0 -9.60000000000001 -0.4
2  37 7 0 -9.60000000000001 -0.4
4 C1 7 0 2 0
0

0101000
+178 0 -225 0 *
Ve
1e-07
-3.62280701754386 0.399999999999994 -29.2767018175483
0 0

0101101
*
Ed
 1e-07 1 1 0
1  25 0 1.5707963267949 3.26471047207603
2  38 7 0 1.5707963267949 3.26471047207603
2  39 24 0 1.5707963267949 3.26471047207603
4 C0 7 0 24 0
0

0101000
+178 0 -176 0 *
Ed
 1e-07 1 1 0
1  26 0 0.4 9.60000000000001
2  40 7 0 0.4 9.60000000000001
2  41 25 0 0.4 9.60000000000001
4 G1 7 0 25 0
0

0101000
+223 0 -176 0 *
Wi

0101100
+222 0 -177 0 +175 0 -174 0 *
Fa
0  1e-07 7 0

0101000
+173 0 *
Ve
1e-07
-3.58555347907037 9.6 -20.599635815813
0 0

0101101
*
Ed
 1e-07 1 1 0
1  27 0 -9.60000000000001 -0.4
2  42 21 0 -9.60000000000001 -0.4
2  43 18 0 -9.60000000000001 -0.4
4 G1 21 0 18 0
0

0101000
+197 0 -171 0 *
Ve
1e-07
-16.5261227400531 9.6 -16.5949590120242
0 0

0101101
*
Ed
 1e-07 1 1 0
1  28 0 0.4 9.60000000000001
2  44 21 0 0.4 9.60000000000001
2  45 22 0 0.4 9.60000000000001
4 G1 21 0 22 0
0

0101000
+169 0 -190 0 *
Ed
 1e-07 1 1 0
1  29 0 3.05593446260129 3.82748916854495
2  46 21 0 3.05593446260129 3.82748916854495
2  47 26 0 3.05593446260129 3.82748916854495
4 C0 21 0 26 0
0

0101000
+171 0 -169 0 *
Wi

0101100
-170 0 -188 0 -168 0 -167 0 *
Fa
0  1e-07 21 0

0101000
+166 0 *
Ve
1e-07
-17.2557890497421 0.399999999999994 -23.0512500955606
0 0

0101101
*
Ed
 1e-07 1 1 0
1  30 0 0.4 9.60000000000001
2  48 14 0 0.4 9.60000000000001
2  49 12 0 0.4 9.60000000000001
4 G1 14 0 12 0
0

0101000
+213 0 -164 0 *
Ve
1e-07
-17.8885206057323 0.399999999999994 -23.457425914586
0 0

0101101
*
Ed
 1e-07 1 1 0
1  31 0 1.34870243442647 3.79310608322391
2  50 14 0 1.34870243442647 3.79310608322391
2  51 27 0 1.34870243442647 3.79310608322391
4 C0 14 0 27 0
0

0101000
+164 0 -162 0 *
Ed
 1e-07 1 1 0
1  32 0 0.4 9.60000000000001
2  52 14 0 0.4 9.60000000000001
2  53 28 0 0.4 9.60000000000001
4 G1 14 0 28 0
0

0101000
+208 0 -162 0 *
Wi

0101100
+205 0 +163 0 +161 0 -160 0 *
Fa
0  1e-07 14 0

0101000
+159 0 *
Ve
1e-07
-11.7333453670698 0.399999999999994 -27.0661893604745
0 0

0101101
*
Ed
 1e-07 1 1 0
1  33 0 3.26471047207603 3.55064552820618
2  54 25 0 3.26471047207603 3.55064552820618
2  55 29 0 3.26471047207603 3.55064552820618
4 C0 25 0 29 0
0

0101000
+176 0 -157 0 *
Ve
1e-07
-11.7333453670698 9.6 -27.0661893604745
0 0

0101101
*
Ed
 1e-07 1 1 0
1  34 0 -9.60000000000001 -0.4
2  56 25 0 -9.60000000000001 -0.4
2  57 30 0 -9.60000000000001 -0.4
4 G1 25 0 30 0
0

0101000
+157 0 -155 0 *
Ed
 1e-07 1 1 0
1  35 0 2.73253977897341 3.01847483510356
2  58 25 0 2.73253977897341 3.01847483510356
2  59 8 0 2.73253977897341 3.01847483510356
4 C0 25 0 8 0
0

0101000
+155 0 -223 0 *
Wi

0101100
+174 0 +156 0 +154 0 +153 0 *
Fa
0  1e-07 25 0

0101000
+152 0 *
Ve
1e-07
-12.2811234217515 9.6 -26.4742595705088
0 0

0101101
*
Ve
1e-07
-12.2811234217515 0.399999999999994 -26.4742595705088
0 0

0101101
*
Ed
 1e-07 1 1 0
1  36 0 0.4 9.60000000000001
2  60 30 0 0.4 9.60000000000001
4 C1 31 0 30 0
0

0101000
+150 0 -149 0 *
Ve
1e-07
-13.7980665639212 0.399999999999994 -22.0687367962036
0 0

0101101
*
Ed
 1e-07 1 1 0
1  37 0 -4.65937199754403 0
4 C0 31 0 32 0
0

0101000
+149 0 -147 0 *
Ed
 1e-07 1 1 0
1  38 0 0.4 9.60000000000001
2  61 12 0 0.4 9.60000000000001
4 G1 31 0 12 0
0

0101000
+218 0 -147 0 *
Ed
 1e-07 1 1 0
1  39 0 -4.65937199754403 0
4 C0 31 0 10 0
0

0101000
+218 0 -150 0 *
Wi

0101100
+148 0 +146 0 -145 0 +144 0 *
Fa
0  1e-07 31 0

0101000
-143 0 *
Ed
 1e-07 1 1 0
1  40 0 5.04400153826362 8.07607552634273
2  62 12 0 5.04400153826362 8.07607552634273
2  63 33 0 5.04400153826362 8.07607552634273
4 C0 12 0 33 0
0

0101000
+147 0 -164 0 *
Wi

0101100
-211 0 +163 0 -141 0 -145 0 *
Fa
0  1e-07 12 0

0101000
+140 0 *
Ve
1e-07
-20.8557210114201 0.399999999999994 -20.8635783386698
0 0

0101101
*
Ed
 1e-07 1 1 0
1  41 0 3.79310608322404 3.92680247904103
2  64 28 0 3.79310608322404 3.92680247904103
2  65 34 0 3.79310608322404 3.92680247904103
4 C0 28 0 34 0
0

0101000
+162 0 -138 0 *
Ve
1e-07
-20.8557210114201 9.6 -20.8635783386698
0 0

0101101
*
Ed
 1e-07 1 1 0
1  42 0 -9.60000000000001 -0.4
2  66 28 0 -9.60000000000001 -0.4
2  67 35 0 -9.60000000000001 -0.4
4 G1 28 0 35 0
0

0101000
+138 0 -136 0 *
Ed
 1e-07 1 1 0
1  43 0 2.35638282813855 2.49007922395555
2  68 28 0 2.35638282813855 2.49007922395555
2  69 13 0 2.35638282813855 2.49007922395555
4 C0 28 0 13 0
0

0101000
+136 0 -208 0 *
Wi

0101100
+160 0 +137 0 +135 0 +134 0 *
Fa
0  1e-07 28 0

0101000
+133 0 *
Ve
1e-07
-20.8307457778752 9.6 -19.4249846933668
0 0

0101101
*
Ve
1e-07
-20.8307457778752 0.399999999999994 -19.4249846933668
0 0

0101101
*
Ed
 1e-07 1 1 0
1  44 0 0.4 9.60000000000001
2  70 35 0 0.4 9.60000000000001
4 C1 36 0 35 0
0

0101000
+131 0 -130 0 *
Ed
 1e-07 1 1 0
1  45 0 1.01754926274775 5.10484332540567
4 C0 36 0 23 0
0

0101000
+130 0 -183 0 *
Ve
1e-07
-17.8414881355442 9.6 -16.637456845541
0 0

0101101
*
Ed
 1e-07 1 1 0
1  46 0 -9.60000000000001 -0.4
2  71 22 0 -9.60000000000001 -0.4
4 C1 36 0 22 0
0

0101000
+183 0 -127 0 *
Ed
 1e-07 1 1 0
1  47 0 -4.08729406265791 0
4 C0 36 0 37 0
0

0101000
+127 0 -131 0 *
Wi

0101100
+129 0 +128 0 +126 0 +125 0 *
Fa
0  1e-07 36 0

0101000
-124 0 *
Ve
1e-07
-2.5 9.6 -21.5959693956039
0 0

0101101
*
Ed
 1e-07 1 1 0
1  48 0 0.4 9.60000000000001
2  72 18 0 0.4 9.60000000000001
4 C1 2 0 18 0
0

0101000
+122 0 -199 0 *
Ed
 1e-07 1 1 0
1  49 0 -7.5587900786226 -0.8704882267646
4 C0 2 0 17 0
0

0101000
+199 0 -178 0 *
Ed
 1e-07 1 1 0
1  50 0 -6.688301851858 0
4 C0 2 0 6 0
0

0101000
+225 0 -122 0 *
Wi

0101100
+121 0 +120 0 +177 0 +119 0 *
Wi

0101100
-232 0 *
Fa
0  1e-07 2 0

0101000
-118 0 -117 0 *
Ve
1e-07
-16.7794695542246 10 -16.9044996260786
0 0

0101101
*
Ve
1e-07
-3.55133208744222 10 -20.9981692477293
0 0

0101101
*
Ed
 1e-07 1 1 0
1  51 0 2.45569613863463 3.2272508445783
2  73 26 0 2.45569613863463 3.2272508445783
4 C0 5 0 26 0
0

0101000
+115 0 -114 0 *
Ve
1e-07
-2.9 10 -21.5959693956039
0 0

0101101
*
Ed
 1e-07 1 1 0
1  52 0 6.19752711619109 7.85398163397448
2  74 38 0 6.19752711619109 7.85398163397448
4 C0 5 0 38 0
0

0101000
+114 0 -112 0 *
Ed
 1e-07 1 1 0
1  53 0 -6.688301851858 0
4 C0 5 0 6 0
0

0101000
+112 0 -228 0 *
Ve
1e-07
-11.5742491587027 10 -26.6991901827054
0 0

0101101
*
Ed
 1e-07 1 1 0
1  54 0 3.26471047207603 3.55064552820617
2  75 8 0 3.26471047207603 3.55064552820617
4 C0 5 0 8 0
0

0101000
+227 0 -109 0 *
Ve
1e-07
-11.9029159915117 10 -26.3440323087259
0 0

0101101
*
Ed
 1e-07 1 1 0
1  55 0 3.55064552820617 4.38077642250576
2  76 39 0 3.55064552820617 4.38077642250576
4 C0 5 0 39 0
0

0101000
+109 0 -107 0 *
Ed
 1e-07 1 1 0
1  56 0 -4.65937199754397 0
4 C0 5 0 10 0
0

0101000
+107 0 -217 0 *
Ve
1e-07
-20.5729315739772 10 -20.5806823611963
0 0

0101101
*
Ed
 1e-07 1 1 0
1  57 0 3.79310608322404 3.92680247904104
2  77 13 0 3.79310608322404 3.92680247904104
4 C0 5 0 13 0
0

0101000
+215 0 -104 0 *
Ve
1e-07
-20.5579464338502 10 -19.7175261740145
0 0

0101101
*
Ed
 1e-07 1 1 0
1  58 0 3.9268024790411 5.53269372882214
2  78 40 0 3.9268024790411 5.53269372882214
4 C0 5 0 40 0
0

0101000
+104 0 -102 0 *
Ve
1e-07
-17.5686887915193 10 -16.9299983261887
0 0

0101101
*
Ed
 1e-07 1 1 0
1  59 0 -4.08729406265784 0
4 C0 5 0 37 0
0

0101000
+102 0 -100 0 *
Ed
 1e-07 1 1 0
1  60 0 5.53269372882202 6.96908182213472
2  79 41 0 5.53269372882202 6.96908182213472
4 C0 5 0 41 0
0

0101000
+100 0 -115 0 *
Wi

0101100
+113 0 +111 0 +110 0 +226 0 +108 0 +106 0 +105 0 +214 0 +103 0 +101 0 
+99 0 +98 0 *
Fa
0  1e-07 5 0

0101000
+97 0 *
Ve
1e-07
-13.4198591336815 0 -21.9385095344208
0 0

0101101
*
Ve
1e-07
-11.9029159915117 0 -26.3440323087259
0 0

0101101
*
Ed
 1e-07 1 1 0
1  61 0 16.3741895145299 21.0335615120738
4 C0 16 0 32 0
0

0101000
+95 0 -94 0 *
Ve
1e-07
-11.5742491587027 0 -26.6991901827054
0 0

0101101
*
Ed
 1e-07 1 1 0
1  62 0 1.90240888467382 2.73253977897342
2  80 42 0 1.90240888467382 2.73253977897342
4 C0 16 0 42 0
0

0101000
+94 0 -92 0 *
Ve
1e-07
-3.57368421052632 0 -28.8797295895138
0 0

0101101
*
Ed
 1e-07 1 1 0
1  63 0 2.73253977897341 3.01847483510356
2  81 29 0 2.73253977897341 3.01847483510356
4 C0 16 0 29 0
0

0101000
+92 0 -90 0 *
Ve
1e-07
-2.9 0 -28.2842712474619
0 0

0101101
*
Ed
 1e-07 1 1 0
1  64 0 3.01847483510357 4.71238898038469
2  82 24 0 3.01847483510357 4.71238898038469
4 C0 16 0 24 0
0

0101000
+90 0 -88 0 *
Ed
 1e-07 1 1 0
1  65 0 -28.2842712474619 -21.5959693956039
4 C0 16 0 17 0
0

0101000
+88 0 -202 0 *
Ve
1e-07
-20.5579464338502 0 -19.7175261740145
0 0

0101101
*
Ed
 1e-07 1 1 0
1  66 0 24.3951566745944 28.4824507372523
4 C0 16 0 23 0
0

0101000
+185 0 -85 0 *
Ve
1e-07
-20.5729315739772 0 -20.5806823611963
0 0

0101101
*
Ed
 1e-07 1 1 0
1  67 0 0.750491578357451 2.35638282813848
2  83 43 0 0.750491578357451 2.35638282813848
4 C0 16 0 43 0
0

0101000
+85 0 -83 0 *
Ve
1e-07
-17.6459643941292 0 -23.1393591225238
0 0

0101101
*
Ed
 1e-07 1 1 0
1  68 0 2.35638282813854 2.49007922395554
2  84 34 0 2.35638282813854 2.49007922395554
4 C0 16 0 34 0
0

0101000
+83 0 -81 0 *
Ed
 1e-07 1 1 0
1  69 0 4.49029508801641 7.52236907609558
2  85 33 0 4.49029508801641 7.52236907609558
4 C0 16 0 33 0
0

0101000
+81 0 -95 0 *
Wi

0101100
+93 0 +91 0 +89 0 +87 0 +86 0 +200 0 +191 0 +184 0 +84 0 +82 0 
+80 0 +79 0 *
Fa
0  1e-07 16 0

0101000
-78 0 *
Ed
 1e-07 1 1 0
1  70 0 4.71238898038469 6.36884349816809
2  86 18 0 4.71238898038469 6.36884349816809
2  87 38 0 4.71238898038469 6.36884349816809
4 C0 18 0 38 0
0

0101000
+122 0 -171 0 *
Wi

0101100
-170 0 +196 0 -121 0 +76 0 *
Fa
0  1e-07 18 0

0101000
+75 0 *
Ed
 1e-07 1 1 0
1  71 0 5.59728879222443 7.03367688553706
2  88 22 0 5.59728879222443 7.03367688553706
2  89 41 0 5.59728879222443 7.03367688553706
4 C0 22 0 41 0
0

0101000
+169 0 -127 0 *
Wi

0101100
-126 0 +182 0 -168 0 +73 0 *
Fa
0  1e-07 22 0

0101000
+72 0 *
Ed
 1e-07 1 1 0
1  72 0 3.92680247904101 5.53269372882211
2  90 35 0 3.92680247904101 5.53269372882211
2  91 43 0 3.92680247904101 5.53269372882211
4 C0 35 0 43 0
0

0101000
+138 0 -130 0 *
Ed
 1e-07 1 1 0
1  73 0 0.75049157835747 2.35638282813858
2  92 35 0 0.75049157835747 2.35638282813858
2  93 40 0 0.75049157835747 2.35638282813858
4 C0 35 0 40 0
0

0101000
+131 0 -136 0 *
Wi

0101100
-135 0 +70 0 -129 0 +69 0 *
Fa
0  1e-07 35 0

0101000
+68 0 *
Ed
 1e-07 1 1 0
1  74 0 3.55064552820624 4.38077642250576
2  94 30 0 3.55064552820624 4.38077642250576
2  95 42 0 3.55064552820624 4.38077642250576
4 C0 30 0 42 0
0

0101000
+157 0 -149 0 *
Ed
 1e-07 1 1 0
1  75 0 1.90240888467383 2.73253977897335
2  96 30 0 1.90240888467383 2.73253977897335
2  97 39 0 1.90240888467383 2.73253977897335
4 C0 30 0 39 0
0

0101000
+150 0 -155 0 *
Wi

0101100
-154 0 +66 0 -148 0 +65 0 *
Fa
0  1e-07 30 0

0101000
+64 0 *
Ed
 1e-07 1 1 0
1  76 0 0 0.56568542494925
2  98 43 0 0 0.56568542494925
4 G1 23 0 43 0
0

0101000
+85 0 -130 0 *
Wi

0101100
-62 0 -84 0 -181 0 -128 0 *
Fa
0  1e-07 23 0

0101000
-61 0 *
Ed
 1e-07 1 1 0
1  77 0 0 0.565685424949198
2  99 43 0 0 0.565685424949198
2  100 34 0 0 0.565685424949198
4 G1 43 0 34 0
0

0101000
+83 0 -138 0 *
Wi

0101100
+62 0 -70 0 -59 0 -82 0 *
Fa
0  1e-07 43 0

0101000
+58 0 *
Ed
 1e-07 1 1 0
1  78 0 0 0.565685424949222
2  101 34 0 0 0.565685424949222
2  102 27 0 0 0.565685424949222
4 G1 34 0 27 0
0

0101000
+81 0 -162 0 *
Wi

0101100
+59 0 -137 0 -56 0 -80 0 *
Fa
0  1e-07 34 0

0101000
+55 0 *
Ed
 1e-07 1 1 1
2  103 27 0 0 2.44440364879741
0

0101000
+81 0 -81 0 *
Ed
 1e-07 1 1 0
1  79 0 0 0.56568542494923
2  104 27 0 0 0.56568542494923
2  105 33 0 0 0.56568542494923
4 G1 27 0 33 0
0

0101000
+81 0 -164 0 *
Wi

0101100
+53 0 +56 0 -161 0 -52 0 *
Fa
0  1e-07 27 0

0101000
+51 0 *
Ed
 1e-07 1 1 0
1  80 0 0 0.565685424949234
2  106 24 0 0 0.565685424949234
4 G1 17 0 24 0
0

0101000
+178 0 -88 0 *
Wi

0101100
+198 0 -86 0 -49 0 -120 0 *
Fa
0  1e-07 17 0

0101000
-48 0 *
Ed
 1e-07 1 1 0
1  81 0 0 0.565685424949201
2  107 33 0 0 0.565685424949201
4 G1 33 0 32 0
0

0101000
+95 0 -147 0 *
Wi

0101100
+79 0 +46 0 +141 0 -52 0 *
Fa
0  1e-07 33 0

0101000
+45 0 *
Ed
 1e-07 1 1 0
1  82 0 0 0.565685424949196
2  108 24 0 0 0.565685424949196
2  109 29 0 0 0.565685424949196
4 G1 24 0 29 0
0

0101000
+176 0 -90 0 *
Wi

0101100
+49 0 -87 0 -43 0 -175 0 *
Fa
0  1e-07 24 0

0101000
+42 0 *
Ed
 1e-07 1 1 0
1  83 0 0 0.565685424949292
2  110 42 0 0 0.565685424949292
4 G1 32 0 42 0
0

0101000
+94 0 -149 0 *
Wi

0101100
+46 0 -146 0 -40 0 -93 0 *
Fa
0  1e-07 32 0

0101000
-39 0 *
Ed
 1e-07 1 1 0
1  84 0 0 0.565685424949218
2  111 29 0 0 0.565685424949218
2  112 42 0 0 0.565685424949218
4 G1 29 0 42 0
0

0101000
+157 0 -92 0 *
Wi

0101100
+43 0 -89 0 -37 0 -156 0 *
Fa
0  1e-07 29 0

0101000
+36 0 *
Wi

0101100
+40 0 -66 0 +37 0 -91 0 *
Fa
0  1e-07 42 0

0101000
+34 0 *
Ed
 1e-07 1 1 0
1  85 0 -0 0.565685424949203
2  113 13 0 -0 0.565685424949203
2  114 40 0 -0 0.565685424949203
4 G1 13 0 40 0
0

0101000
+104 0 -136 0 *
Wi

0101100
+207 0 -134 0 -32 0 -103 0 *
Fa
0  1e-07 13 0

0101000
+31 0 *
Ed
 1e-07 1 1 0
1  86 0 0 0.565685424949296
2  115 39 0 0 0.565685424949296
4 G1 10 0 39 0
0

0101000
+150 0 -107 0 *
Wi

0101100
+216 0 -105 0 -29 0 -144 0 *
Fa
0  1e-07 10 0

0101000
+28 0 *
Ed
 1e-07 1 1 0
1  87 0 0 0.565685424949254
2  116 40 0 0 0.565685424949254
4 G1 40 0 37 0
0

0101000
+102 0 -131 0 *
Wi

0101100
+32 0 -69 0 -26 0 -101 0 *
Fa
0  1e-07 40 0

0101000
+25 0 *
Ed
 1e-07 1 1 0
1  88 0 0 0.565685424949222
2  117 39 0 0 0.565685424949222
2  118 8 0 0 0.565685424949222
4 G1 39 0 8 0
0

0101000
+155 0 -109 0 *
Wi

0101100
+29 0 -106 0 -23 0 -65 0 *
Fa
0  1e-07 39 0

0101000
+22 0 *
Ed
 1e-07 1 1 0
1  89 0 0 0.565685424949206
2  119 41 0 0 0.565685424949206
4 G1 37 0 41 0
0

0101000
+100 0 -127 0 *
Wi

0101100
+26 0 -125 0 -20 0 -99 0 *
Fa
0  1e-07 37 0

0101000
+19 0 *
Wi

0101100
+23 0 -108 0 -221 0 -153 0 *
Fa
0  1e-07 8 0

0101000
+17 0 *
Ed
 1e-07 1 1 0
1  90 0 0 0.565685424949259
2  120 41 0 0 0.565685424949259
2  121 26 0 0 0.565685424949259
4 G1 41 0 26 0
0

0101000
+115 0 -169 0 *
Wi

0101100
+20 0 -73 0 -15 0 -98 0 *
Fa
0  1e-07 41 0

0101000
+14 0 *
Ed
 1e-07 1 1 0
1  91 0 0 0.565685424949197
2  122 26 0 0 0.565685424949197
2  123 38 0 0 0.565685424949197
4 G1 26 0 38 0
0

0101000
+114 0 -171 0 *
Wi

0101100
+113 0 +12 0 +167 0 -15 0 *
Fa
0  1e-07 26 0

0101000
+11 0 *
Ed
 1e-07 1 1 0
1  92 0 0 0.565685424949238
2  124 38 0 0 0.565685424949238
4 G1 6 0 38 0
0

0101000
+122 0 -112 0 *
Wi

0101100
+224 0 -110 0 -9 0 -119 0 *
Fa
0  1e-07 6 0

0101000
+8 0 *
Wi

0101100
+12 0 -76 0 +9 0 -111 0 *
Fa
0  1e-07 38 0

0101000
+6 0 *
Wi

0101100
+231 0 *
Fa
0  1e-07 3 0

0101000
+4 0 *
Sh

0101100
-229 0 +219 0 -209 0 +203 0 +193 0 -186 0 +179 0 +172 0 -165 0 +158 0 
+151 0 -142 0 -139 0 +132 0 -123 0 -116 0 +96 0 -77 0 +74 0 +71 0 
+67 0 +63 0 -60 0 +57 0 +54 0 +50 0 -47 0 -44 0 +41 0 -38 0 
+35 0 +33 0 +30 0 +27 0 +24 0 +21 0 +18 0 +16 0 +13 0 -10 0 
+7 0 +5 0 +3 0 *
So

0100000
+2 0 *

+1 1 ]]>
      </Part>
      <ElementMap/>
    </Property>
    <Property name="TreeRank" type="App::PropertyInteger" status="2184">
      <Integer value="345"/>
    </Property>
    <Property name="Visibility" type="App::PropertyBool" status="648">
      <Bool value="true"/>
    </Property>
  </Properties>
</Object>
</Document>
